[
  {
    "prefLabel": "Aruba",
    "resourceIdentifier": "http://standaarden.overheid.nl/owms/terms/Aruba"
  },
  {
    "prefLabel": "Curaçao",
    "resourceIdentifier": "http://standaarden.overheid.nl/owms/terms/Curacao"
  },
  {
    "prefLabel": "Nederland",
    "resourceIdentifier": "http://standaarden.overheid.nl/owms/terms/Nederland"
  },
  {
    "prefLabel": "Nederlandse Antillen",
    "resourceIdentifier": "http://standaarden.overheid.nl/owms/terms/Nederlandse_Antillen",
    "endDate": "2010-10-10"
  },
  {
    "prefLabel": "Sint Maarten",
    "resourceIdentifier": "http://standaarden.overheid.nl/owms/terms/Sint_Maarten_(Nederlandse_Antillen)"
  }
]