<?xml version="1.0" encoding="UTF-8"?><searchRetrieveResponse xmlns="http://www.loc.gov/zing/srw/" xmlns:xsi="http://www.w3.org/2001/XMLSchema-instance" xmlns:overheid="http://standaarden.overheid.nl/owms/terms/" xmlns:dcterms="http://purl.org/dc/terms/" xmlns:overheidproduct="http://standaarden.overheid.nl/product/terms/" xsi:schemaLocation="http://www.loc.gov/zing/srw/ srw-types.xsd"><version>1.2</version><numberOfRecords>27</numberOfRecords><records><record><recordSchema>http://standaarden.overheid.nl/sru/</recordSchema><recordPacking>xml</recordPacking><recordData><gzd xmlns="http://standaarden.overheid.nl/sru" xmlns:overheidtr="http://standaarden.overheid.nl/tr/meta/" xmlns:overheidvd="http://standaarden.overheid.nl/vd/meta/" xmlns:overheidvb="http://standaarden.overheid.nl/vb/terms" xsi:schemaLocation="http://standaarden.overheid.nl/sru gzd.xsd"><originalData><overheidproduct:scproduct owms-version="4.0"><overheidproduct:meta><overheidproduct:owmskern><dcterms:identifier><![CDATA[https://www.voerendaal.nl/producten/koninklijke-onderscheiding-lintje]]></dcterms:identifier><dcterms:title><![CDATA[Koninklijke onderscheiding, lintje]]></dcterms:title><dcterms:language><![CDATA[nl]]></dcterms:language><dcterms:type scheme="overheid:Informatietype">productbeschrijving</dcterms:type><dcterms:modified>2023-04-17</dcterms:modified><dcterms:spatial scheme="overheid:Gemeente" resourceIdentifier="http://standaarden.overheid.nl/owms/terms/Voerendaal_(gemeente)"><![CDATA[Voerendaal]]></dcterms:spatial><overheid:authority scheme="overheid:Gemeente" resourceIdentifier="http://standaarden.overheid.nl/owms/terms/Voerendaal_(gemeente)"><![CDATA[Voerendaal]]></overheid:authority></overheidproduct:owmskern><overheidproduct:owmsmantel><dcterms:audience scheme="overheid:Doelgroep">ondernemer</dcterms:audience><dcterms:abstract><![CDATA[Wilt u iemand voordragen voor een Koninklijke Onderscheiding?Bekijk de informatie op lintjes; Neem contact op met de gemeente via het telefoonnummer 045 - 575 33 99;Vraag het formulier voor aanvraag van de Koninklijke Onderscheiding aan via kabinet@voerendaal.nl;Verzamel alle gegevens;Vul het voorstelformulier in en stuur het&amp;nbsp;met alle bijlagen via email naar&amp;nbsp;kabinet@voerendaal.nl;Let op: het voorstel moet uiterlijk 1 juli ingediend worden in het jaar voorafgaand aan de uitreiking.]]></dcterms:abstract></overheidproduct:owmsmantel><overheidproduct:scmeta><overheidproduct:productID><![CDATA[62a47328-eca2-4a5b-b383-2aa712b8ef26]]></overheidproduct:productID><overheidproduct:onlineAanvragen>nee</overheidproduct:onlineAanvragen></overheidproduct:scmeta></overheidproduct:meta><overheidproduct:body><overheidproduct:productHTML xsi:schemaLocation="http://www.w3.org/1999/xhtml http://www.w3.org/2002/08/xhtml/xhtml1-strict.xsd"/></overheidproduct:body></overheidproduct:scproduct></originalData><enrichedData><authorityScheme>Gemeente</authorityScheme><authorityUri>http://standaarden.overheid.nl/owms/terms/Voerendaal_(gemeente)</authorityUri><spatialType>Gemeente</spatialType><spatialUri>http://standaarden.overheid.nl/owms/terms/Voerendaal_(gemeente)</spatialUri></enrichedData></gzd></recordData><recordPosition>1</recordPosition><extraRecordData><version:version xmlns:version="http://standaarden.overheid.nl/sru/version">full</version:version><dtf:timestamp xmlns:dtf="http://standaarden.overheid.nl/sru/dtf">2023-10-18T10:55:41.563791+02:00</dtf:timestamp><rel:rank xmlns:rel="http://standaarden.overheid.nl/sru/rel">0%</rel:rank><accept:accept xmlns:accept="info:srw/1/extensions/accept">any</accept:accept></extraRecordData></record><record><recordSchema>http://standaarden.overheid.nl/sru/</recordSchema><recordPacking>xml</recordPacking><recordData><gzd xmlns="http://standaarden.overheid.nl/sru" xmlns:overheidtr="http://standaarden.overheid.nl/tr/meta/" xmlns:overheidvd="http://standaarden.overheid.nl/vd/meta/" xmlns:overheidvb="http://standaarden.overheid.nl/vb/terms" xsi:schemaLocation="http://standaarden.overheid.nl/sru gzd.xsd"><originalData><overheidproduct:scproduct owms-version="4.0"><overheidproduct:meta><overheidproduct:owmskern><dcterms:identifier><![CDATA[https://www.voerendaal.nl/aanvragen-en-regelen/persoonsgegevens/gebruik-en-wijziging-achternaam]]></dcterms:identifier><dcterms:title><![CDATA[Gebruik en wijziging achternaam]]></dcterms:title><dcterms:language><![CDATA[nl]]></dcterms:language><dcterms:type scheme="overheid:Informatietype">productbeschrijving</dcterms:type><dcterms:modified>2023-05-08</dcterms:modified><dcterms:spatial scheme="overheid:Gemeente" resourceIdentifier="http://standaarden.overheid.nl/owms/terms/Voerendaal_(gemeente)"><![CDATA[Voerendaal]]></dcterms:spatial><overheid:authority scheme="overheid:Gemeente" resourceIdentifier="http://standaarden.overheid.nl/owms/terms/Voerendaal_(gemeente)"><![CDATA[Voerendaal]]></overheid:authority></overheidproduct:owmskern><overheidproduct:owmsmantel><dcterms:audience scheme="overheid:Doelgroep">particulier</dcterms:audience><dcterms:subject scheme="overheid:TaxonomieBeleidsagenda">Recht</dcterms:subject><dcterms:abstract><![CDATA[Wilt u uw achternaam laten wijzigen? Dat moet aangevraagd worden via Justis en hier zijn strenge voorwaarden aan verbonden.]]></dcterms:abstract></overheidproduct:owmsmantel><overheidproduct:scmeta><overheidproduct:productID><![CDATA[82]]></overheidproduct:productID><overheidproduct:onlineAanvragen>nee</overheidproduct:onlineAanvragen><overheidproduct:uniformeProductnaam scheme="overheid:UniformeProductnaam" resourceIdentifier="http://standaarden.overheid.nl/owms/terms/achternaamwijziging">achternaamwijziging</overheidproduct:uniformeProductnaam></overheidproduct:scmeta></overheidproduct:meta><overheidproduct:body><overheidproduct:productHTML xsi:schemaLocation="http://www.w3.org/1999/xhtml http://www.w3.org/2002/08/xhtml/xhtml1-strict.xsd"/></overheidproduct:body></overheidproduct:scproduct></originalData><enrichedData><authorityScheme>Gemeente</authorityScheme><authorityUri>http://standaarden.overheid.nl/owms/terms/Voerendaal_(gemeente)</authorityUri><spatialType>Gemeente</spatialType><spatialUri>http://standaarden.overheid.nl/owms/terms/Voerendaal_(gemeente)</spatialUri><uniformeProductnaamUri>http://standaarden.overheid.nl/owms/terms/achternaamwijziging</uniformeProductnaamUri></enrichedData></gzd></recordData><recordPosition>2</recordPosition><extraRecordData><version:version xmlns:version="http://standaarden.overheid.nl/sru/version">full</version:version><dtf:timestamp xmlns:dtf="http://standaarden.overheid.nl/sru/dtf">2023-10-18T10:55:41.563791+02:00</dtf:timestamp><rel:rank xmlns:rel="http://standaarden.overheid.nl/sru/rel">0%</rel:rank><accept:accept xmlns:accept="info:srw/1/extensions/accept">any</accept:accept></extraRecordData></record><record><recordSchema>http://standaarden.overheid.nl/sru/</recordSchema><recordPacking>xml</recordPacking><recordData><gzd xmlns="http://standaarden.overheid.nl/sru" xmlns:overheidtr="http://standaarden.overheid.nl/tr/meta/" xmlns:overheidvd="http://standaarden.overheid.nl/vd/meta/" xmlns:overheidvb="http://standaarden.overheid.nl/vb/terms" xsi:schemaLocation="http://standaarden.overheid.nl/sru gzd.xsd"><originalData><overheidproduct:scproduct owms-version="4.0"><overheidproduct:meta><overheidproduct:owmskern><dcterms:identifier><![CDATA[https://www.voerendaal.nl/aanvragen-en-regelen/geboorte-trouwen-overlijden/kind-erkennen-ouderlijk-gezag]]></dcterms:identifier><dcterms:title><![CDATA[Kind erkennen, Ouderlijk gezag]]></dcterms:title><dcterms:language><![CDATA[nl]]></dcterms:language><dcterms:type scheme="overheid:Informatietype">productbeschrijving</dcterms:type><dcterms:modified>2023-05-08</dcterms:modified><dcterms:spatial scheme="overheid:Gemeente" resourceIdentifier="http://standaarden.overheid.nl/owms/terms/Voerendaal_(gemeente)"><![CDATA[Voerendaal]]></dcterms:spatial><overheid:authority scheme="overheid:Gemeente" resourceIdentifier="http://standaarden.overheid.nl/owms/terms/Voerendaal_(gemeente)"><![CDATA[Voerendaal]]></overheid:authority></overheidproduct:owmskern><overheidproduct:owmsmantel><dcterms:audience scheme="overheid:Doelgroep">particulier</dcterms:audience><dcterms:subject scheme="overheid:TaxonomieBeleidsagenda">Recht</dcterms:subject><dcterms:abstract><![CDATA[In bepaalde gevallen moet u uw kind erkennen om als tweede ouder in de geboorteakte te worden vermeld. Dit moet aan de balie.]]></dcterms:abstract></overheidproduct:owmsmantel><overheidproduct:scmeta><overheidproduct:productID><![CDATA[52]]></overheidproduct:productID><overheidproduct:onlineAanvragen>nee</overheidproduct:onlineAanvragen><overheidproduct:uniformeProductnaam scheme="overheid:UniformeProductnaam" resourceIdentifier="http://standaarden.overheid.nl/owms/terms/erkenning_kind">erkenning kind</overheidproduct:uniformeProductnaam></overheidproduct:scmeta></overheidproduct:meta><overheidproduct:body><overheidproduct:productHTML xsi:schemaLocation="http://www.w3.org/1999/xhtml http://www.w3.org/2002/08/xhtml/xhtml1-strict.xsd"/></overheidproduct:body></overheidproduct:scproduct></originalData><enrichedData><authorityScheme>Gemeente</authorityScheme><authorityUri>http://standaarden.overheid.nl/owms/terms/Voerendaal_(gemeente)</authorityUri><spatialType>Gemeente</spatialType><spatialUri>http://standaarden.overheid.nl/owms/terms/Voerendaal_(gemeente)</spatialUri><uniformeProductnaamUri>http://standaarden.overheid.nl/owms/terms/erkenning_kind</uniformeProductnaamUri></enrichedData></gzd></recordData><recordPosition>3</recordPosition><extraRecordData><version:version xmlns:version="http://standaarden.overheid.nl/sru/version">full</version:version><dtf:timestamp xmlns:dtf="http://standaarden.overheid.nl/sru/dtf">2023-10-18T10:55:41.563791+02:00</dtf:timestamp><rel:rank xmlns:rel="http://standaarden.overheid.nl/sru/rel">0%</rel:rank><accept:accept xmlns:accept="info:srw/1/extensions/accept">any</accept:accept></extraRecordData></record><record><recordSchema>http://standaarden.overheid.nl/sru/</recordSchema><recordPacking>xml</recordPacking><recordData><gzd xmlns="http://standaarden.overheid.nl/sru" xmlns:overheidtr="http://standaarden.overheid.nl/tr/meta/" xmlns:overheidvd="http://standaarden.overheid.nl/vd/meta/" xmlns:overheidvb="http://standaarden.overheid.nl/vb/terms" xsi:schemaLocation="http://standaarden.overheid.nl/sru gzd.xsd"><originalData><overheidproduct:scproduct owms-version="4.0"><overheidproduct:meta><overheidproduct:owmskern><dcterms:identifier><![CDATA[https://www.voerendaal.nl/aanvragen-en-regelen/bouwen-en-wonen/bestemmingsplan]]></dcterms:identifier><dcterms:title><![CDATA[Bestemmingsplan]]></dcterms:title><dcterms:language><![CDATA[nl]]></dcterms:language><dcterms:type scheme="overheid:Informatietype">productbeschrijving</dcterms:type><dcterms:modified>2023-05-08</dcterms:modified><dcterms:spatial scheme="overheid:Gemeente" resourceIdentifier="http://standaarden.overheid.nl/owms/terms/Voerendaal_(gemeente)"><![CDATA[Voerendaal]]></dcterms:spatial><overheid:authority scheme="overheid:Gemeente" resourceIdentifier="http://standaarden.overheid.nl/owms/terms/Voerendaal_(gemeente)"><![CDATA[Voerendaal]]></overheid:authority></overheidproduct:owmskern><overheidproduct:owmsmantel><dcterms:audience scheme="overheid:Doelgroep">particulier</dcterms:audience><dcterms:subject scheme="overheid:TaxonomieBeleidsagenda">Ruimte en infrastructuur</dcterms:subject><dcterms:abstract><![CDATA[De gemeente maakt bestemmingsplannen voor de ruimtelijke inrichting van haar totale grondgebied.]]></dcterms:abstract></overheidproduct:owmsmantel><overheidproduct:scmeta><overheidproduct:productID><![CDATA[80]]></overheidproduct:productID><overheidproduct:onlineAanvragen>nee</overheidproduct:onlineAanvragen><overheidproduct:uniformeProductnaam scheme="overheid:UniformeProductnaam" resourceIdentifier="http://standaarden.overheid.nl/owms/terms/bestemmingsplan_inzage">bestemmingsplan inzage</overheidproduct:uniformeProductnaam></overheidproduct:scmeta></overheidproduct:meta><overheidproduct:body><overheidproduct:productHTML xsi:schemaLocation="http://www.w3.org/1999/xhtml http://www.w3.org/2002/08/xhtml/xhtml1-strict.xsd"/></overheidproduct:body></overheidproduct:scproduct></originalData><enrichedData><authorityScheme>Gemeente</authorityScheme><authorityUri>http://standaarden.overheid.nl/owms/terms/Voerendaal_(gemeente)</authorityUri><spatialType>Gemeente</spatialType><spatialUri>http://standaarden.overheid.nl/owms/terms/Voerendaal_(gemeente)</spatialUri><uniformeProductnaamUri>http://standaarden.overheid.nl/owms/terms/bestemmingsplan_inzage</uniformeProductnaamUri></enrichedData></gzd></recordData><recordPosition>4</recordPosition><extraRecordData><version:version xmlns:version="http://standaarden.overheid.nl/sru/version">full</version:version><dtf:timestamp xmlns:dtf="http://standaarden.overheid.nl/sru/dtf">2023-10-18T10:55:41.563791+02:00</dtf:timestamp><rel:rank xmlns:rel="http://standaarden.overheid.nl/sru/rel">0%</rel:rank><accept:accept xmlns:accept="info:srw/1/extensions/accept">any</accept:accept></extraRecordData></record><record><recordSchema>http://standaarden.overheid.nl/sru/</recordSchema><recordPacking>xml</recordPacking><recordData><gzd xmlns="http://standaarden.overheid.nl/sru" xmlns:overheidtr="http://standaarden.overheid.nl/tr/meta/" xmlns:overheidvd="http://standaarden.overheid.nl/vd/meta/" xmlns:overheidvb="http://standaarden.overheid.nl/vb/terms" xsi:schemaLocation="http://standaarden.overheid.nl/sru gzd.xsd"><originalData><overheidproduct:scproduct owms-version="4.0"><overheidproduct:meta><overheidproduct:owmskern><dcterms:identifier><![CDATA[https://www.voerendaal.nl/aanvragen-en-regelen/paspoort-id-rijbewijs-en-uittreksels/paspoort-/-identiteitskaart]]></dcterms:identifier><dcterms:title><![CDATA[Paspoort / identiteitskaart]]></dcterms:title><dcterms:language><![CDATA[nl]]></dcterms:language><dcterms:type scheme="overheid:Informatietype">productbeschrijving</dcterms:type><dcterms:modified>2023-05-08</dcterms:modified><dcterms:spatial scheme="overheid:Gemeente" resourceIdentifier="http://standaarden.overheid.nl/owms/terms/Voerendaal_(gemeente)"><![CDATA[Voerendaal]]></dcterms:spatial><overheid:authority scheme="overheid:Gemeente" resourceIdentifier="http://standaarden.overheid.nl/owms/terms/Voerendaal_(gemeente)"><![CDATA[Voerendaal]]></overheid:authority></overheidproduct:owmskern><overheidproduct:owmsmantel><dcterms:audience scheme="overheid:Doelgroep">particulier</dcterms:audience><dcterms:audience scheme="overheid:Doelgroep">ondernemer</dcterms:audience><dcterms:subject scheme="overheid:TaxonomieBeleidsagenda">Recht</dcterms:subject><dcterms:abstract><![CDATA[Uw paspoort of ID-kaart vraagt u persoonlijk aan en haalt u persoonlijk op in het gemeentehuis. Uw paspoort of ID-kaart ligt na 5 werkdagen voor u klaar. Maak een afspraak voor het aanvragen.]]></dcterms:abstract></overheidproduct:owmsmantel><overheidproduct:scmeta><overheidproduct:productID><![CDATA[95]]></overheidproduct:productID><overheidproduct:onlineAanvragen>nee</overheidproduct:onlineAanvragen><overheidproduct:uniformeProductnaam scheme="overheid:UniformeProductnaam" resourceIdentifier="http://standaarden.overheid.nl/owms/terms/paspoort">paspoort</overheidproduct:uniformeProductnaam><overheidproduct:uniformeProductnaam scheme="overheid:UniformeProductnaam" resourceIdentifier="http://standaarden.overheid.nl/owms/terms/paspTweede">paspoort tweede</overheidproduct:uniformeProductnaam><overheidproduct:uniformeProductnaam scheme="overheid:UniformeProductnaam" resourceIdentifier="http://standaarden.overheid.nl/owms/terms/vluchtelingenpaspoort">vluchtelingenpaspoort</overheidproduct:uniformeProductnaam><overheidproduct:uniformeProductnaam scheme="overheid:UniformeProductnaam" resourceIdentifier="http://standaarden.overheid.nl/owms/terms/vreemdelingenpaspoort">vreemdelingenpaspoort</overheidproduct:uniformeProductnaam><overheidproduct:uniformeProductnaam scheme="overheid:UniformeProductnaam" resourceIdentifier="http://standaarden.overheid.nl/owms/terms/zakenpaspoort">zakenpaspoort</overheidproduct:uniformeProductnaam></overheidproduct:scmeta></overheidproduct:meta><overheidproduct:body><overheidproduct:productHTML xsi:schemaLocation="http://www.w3.org/1999/xhtml http://www.w3.org/2002/08/xhtml/xhtml1-strict.xsd"/></overheidproduct:body></overheidproduct:scproduct></originalData><enrichedData><authorityScheme>Gemeente</authorityScheme><authorityUri>http://standaarden.overheid.nl/owms/terms/Voerendaal_(gemeente)</authorityUri><spatialType>Gemeente</spatialType><spatialUri>http://standaarden.overheid.nl/owms/terms/Voerendaal_(gemeente)</spatialUri><uniformeProductnaamUri>http://standaarden.overheid.nl/owms/terms/paspoort</uniformeProductnaamUri><uniformeProductnaamUri>http://standaarden.overheid.nl/owms/terms/paspTweede</uniformeProductnaamUri><uniformeProductnaamUri>http://standaarden.overheid.nl/owms/terms/vluchtelingenpaspoort</uniformeProductnaamUri><uniformeProductnaamUri>http://standaarden.overheid.nl/owms/terms/vreemdelingenpaspoort</uniformeProductnaamUri><uniformeProductnaamUri>http://standaarden.overheid.nl/owms/terms/zakenpaspoort</uniformeProductnaamUri></enrichedData></gzd></recordData><recordPosition>5</recordPosition><extraRecordData><version:version xmlns:version="http://standaarden.overheid.nl/sru/version">full</version:version><dtf:timestamp xmlns:dtf="http://standaarden.overheid.nl/sru/dtf">2023-10-18T10:55:41.563791+02:00</dtf:timestamp><rel:rank xmlns:rel="http://standaarden.overheid.nl/sru/rel">0%</rel:rank><accept:accept xmlns:accept="info:srw/1/extensions/accept">any</accept:accept></extraRecordData></record><record><recordSchema>http://standaarden.overheid.nl/sru/</recordSchema><recordPacking>xml</recordPacking><recordData><gzd xmlns="http://standaarden.overheid.nl/sru" xmlns:overheidtr="http://standaarden.overheid.nl/tr/meta/" xmlns:overheidvd="http://standaarden.overheid.nl/vd/meta/" xmlns:overheidvb="http://standaarden.overheid.nl/vb/terms" xsi:schemaLocation="http://standaarden.overheid.nl/sru gzd.xsd"><originalData><overheidproduct:scproduct owms-version="4.0"><overheidproduct:meta><overheidproduct:owmskern><dcterms:identifier><![CDATA[https://www.voerendaal.nl/aanvragen-en-regelen/belastingen/woz-waarde]]></dcterms:identifier><dcterms:title><![CDATA[WOZ-waarde]]></dcterms:title><dcterms:language><![CDATA[nl]]></dcterms:language><dcterms:type scheme="overheid:Informatietype">productbeschrijving</dcterms:type><dcterms:modified>2023-05-08</dcterms:modified><dcterms:spatial scheme="overheid:Gemeente" resourceIdentifier="http://standaarden.overheid.nl/owms/terms/Voerendaal_(gemeente)"><![CDATA[Voerendaal]]></dcterms:spatial><overheid:authority scheme="overheid:Gemeente" resourceIdentifier="http://standaarden.overheid.nl/owms/terms/Voerendaal_(gemeente)"><![CDATA[Voerendaal]]></overheid:authority></overheidproduct:owmskern><overheidproduct:owmsmantel><dcterms:audience scheme="overheid:Doelgroep">particulier</dcterms:audience><dcterms:subject scheme="overheid:TaxonomieBeleidsagenda">Financiën</dcterms:subject><dcterms:abstract><![CDATA[Vindt u dat de WOZ-waarde niet klopt, dan kunt u binnen 6 weken bezwaar maken. ]]></dcterms:abstract></overheidproduct:owmsmantel><overheidproduct:scmeta><overheidproduct:productID><![CDATA[142]]></overheidproduct:productID><overheidproduct:onlineAanvragen>nee</overheidproduct:onlineAanvragen><overheidproduct:uniformeProductnaam scheme="overheid:UniformeProductnaam" resourceIdentifier="http://standaarden.overheid.nl/owms/terms/belastingaanslag_bezwaar">belastingaanslag bezwaar</overheidproduct:uniformeProductnaam></overheidproduct:scmeta></overheidproduct:meta><overheidproduct:body><overheidproduct:productHTML xsi:schemaLocation="http://www.w3.org/1999/xhtml http://www.w3.org/2002/08/xhtml/xhtml1-strict.xsd"/></overheidproduct:body></overheidproduct:scproduct></originalData><enrichedData><authorityScheme>Gemeente</authorityScheme><authorityUri>http://standaarden.overheid.nl/owms/terms/Voerendaal_(gemeente)</authorityUri><spatialType>Gemeente</spatialType><spatialUri>http://standaarden.overheid.nl/owms/terms/Voerendaal_(gemeente)</spatialUri><uniformeProductnaamUri>http://standaarden.overheid.nl/owms/terms/belastingaanslag_bezwaar</uniformeProductnaamUri></enrichedData></gzd></recordData><recordPosition>6</recordPosition><extraRecordData><version:version xmlns:version="http://standaarden.overheid.nl/sru/version">full</version:version><dtf:timestamp xmlns:dtf="http://standaarden.overheid.nl/sru/dtf">2023-10-18T10:55:41.563791+02:00</dtf:timestamp><rel:rank xmlns:rel="http://standaarden.overheid.nl/sru/rel">0%</rel:rank><accept:accept xmlns:accept="info:srw/1/extensions/accept">any</accept:accept></extraRecordData></record><record><recordSchema>http://standaarden.overheid.nl/sru/</recordSchema><recordPacking>xml</recordPacking><recordData><gzd xmlns="http://standaarden.overheid.nl/sru" xmlns:overheidtr="http://standaarden.overheid.nl/tr/meta/" xmlns:overheidvd="http://standaarden.overheid.nl/vd/meta/" xmlns:overheidvb="http://standaarden.overheid.nl/vb/terms" xsi:schemaLocation="http://standaarden.overheid.nl/sru gzd.xsd"><originalData><overheidproduct:scproduct owms-version="4.0"><overheidproduct:meta><overheidproduct:owmskern><dcterms:identifier><![CDATA[https://www.voerendaal.nl/aanvragen-en-regelen/bouwen-en-wonen/starterslening]]></dcterms:identifier><dcterms:title><![CDATA[Starterslening]]></dcterms:title><dcterms:language><![CDATA[nl]]></dcterms:language><dcterms:type scheme="overheid:Informatietype">productbeschrijving</dcterms:type><dcterms:modified>2023-05-08</dcterms:modified><dcterms:spatial scheme="overheid:Gemeente" resourceIdentifier="http://standaarden.overheid.nl/owms/terms/Voerendaal_(gemeente)"><![CDATA[Voerendaal]]></dcterms:spatial><overheid:authority scheme="overheid:Gemeente" resourceIdentifier="http://standaarden.overheid.nl/owms/terms/Voerendaal_(gemeente)"><![CDATA[Voerendaal]]></overheid:authority></overheidproduct:owmskern><overheidproduct:owmsmantel><dcterms:audience scheme="overheid:Doelgroep">particulier</dcterms:audience><dcterms:subject scheme="overheid:TaxonomieBeleidsagenda">Huisvesting</dcterms:subject><dcterms:abstract><![CDATA[Is de prijs van uw eerste koophuis hoger dan het bedrag dat u bij de bank kunt lenen? Dan helpen we u met de starterslening van maximaal €56.000,-.]]></dcterms:abstract></overheidproduct:owmsmantel><overheidproduct:scmeta><overheidproduct:productID><![CDATA[34]]></overheidproduct:productID><overheidproduct:onlineAanvragen>nee</overheidproduct:onlineAanvragen><overheidproduct:uniformeProductnaam scheme="overheid:UniformeProductnaam" resourceIdentifier="http://standaarden.overheid.nl/owms/terms/starterslening">starterslening</overheidproduct:uniformeProductnaam></overheidproduct:scmeta></overheidproduct:meta><overheidproduct:body><overheidproduct:productHTML xsi:schemaLocation="http://www.w3.org/1999/xhtml http://www.w3.org/2002/08/xhtml/xhtml1-strict.xsd"/></overheidproduct:body></overheidproduct:scproduct></originalData><enrichedData><authorityScheme>Gemeente</authorityScheme><authorityUri>http://standaarden.overheid.nl/owms/terms/Voerendaal_(gemeente)</authorityUri><spatialType>Gemeente</spatialType><spatialUri>http://standaarden.overheid.nl/owms/terms/Voerendaal_(gemeente)</spatialUri><uniformeProductnaamUri>http://standaarden.overheid.nl/owms/terms/starterslening</uniformeProductnaamUri></enrichedData></gzd></recordData><recordPosition>7</recordPosition><extraRecordData><version:version xmlns:version="http://standaarden.overheid.nl/sru/version">full</version:version><dtf:timestamp xmlns:dtf="http://standaarden.overheid.nl/sru/dtf">2023-10-18T10:55:41.563791+02:00</dtf:timestamp><rel:rank xmlns:rel="http://standaarden.overheid.nl/sru/rel">0%</rel:rank><accept:accept xmlns:accept="info:srw/1/extensions/accept">any</accept:accept></extraRecordData></record><record><recordSchema>http://standaarden.overheid.nl/sru/</recordSchema><recordPacking>xml</recordPacking><recordData><gzd xmlns="http://standaarden.overheid.nl/sru" xmlns:overheidtr="http://standaarden.overheid.nl/tr/meta/" xmlns:overheidvd="http://standaarden.overheid.nl/vd/meta/" xmlns:overheidvb="http://standaarden.overheid.nl/vb/terms" xsi:schemaLocation="http://standaarden.overheid.nl/sru gzd.xsd"><originalData><overheidproduct:scproduct owms-version="4.0"><overheidproduct:meta><overheidproduct:owmskern><dcterms:identifier><![CDATA[https://www.voerendaal.nl/aanvragen-en-regelen/overig/verloren-of-gevonden]]></dcterms:identifier><dcterms:title><![CDATA[Verloren of gevonden]]></dcterms:title><dcterms:language><![CDATA[nl]]></dcterms:language><dcterms:type scheme="overheid:Informatietype">productbeschrijving</dcterms:type><dcterms:modified>2023-05-08</dcterms:modified><dcterms:spatial scheme="overheid:Gemeente" resourceIdentifier="http://standaarden.overheid.nl/owms/terms/Voerendaal_(gemeente)"><![CDATA[Voerendaal]]></dcterms:spatial><overheid:authority scheme="overheid:Gemeente" resourceIdentifier="http://standaarden.overheid.nl/owms/terms/Voerendaal_(gemeente)"><![CDATA[Voerendaal]]></overheid:authority></overheidproduct:owmskern><overheidproduct:owmsmantel><dcterms:audience scheme="overheid:Doelgroep">particulier</dcterms:audience><dcterms:subject scheme="overheid:TaxonomieBeleidsagenda">Recht</dcterms:subject><dcterms:abstract><![CDATA[Heeft u voorwerpen gevonden of bent u zelf iets verloren? Doe hiervan aangifte bij de gemeente, niet bij de politie. Denkt u dat het om diefstal gaat, dan verwijzen we u wél door naar politie.]]></dcterms:abstract></overheidproduct:owmsmantel><overheidproduct:scmeta><overheidproduct:productID><![CDATA[68]]></overheidproduct:productID><overheidproduct:onlineAanvragen>nee</overheidproduct:onlineAanvragen><overheidproduct:uniformeProductnaam scheme="overheid:UniformeProductnaam" resourceIdentifier="http://standaarden.overheid.nl/owms/terms/gevVerlVoorwerp">gevonden of verloren voorwerp</overheidproduct:uniformeProductnaam></overheidproduct:scmeta></overheidproduct:meta><overheidproduct:body><overheidproduct:productHTML xsi:schemaLocation="http://www.w3.org/1999/xhtml http://www.w3.org/2002/08/xhtml/xhtml1-strict.xsd"/></overheidproduct:body></overheidproduct:scproduct></originalData><enrichedData><authorityScheme>Gemeente</authorityScheme><authorityUri>http://standaarden.overheid.nl/owms/terms/Voerendaal_(gemeente)</authorityUri><spatialType>Gemeente</spatialType><spatialUri>http://standaarden.overheid.nl/owms/terms/Voerendaal_(gemeente)</spatialUri><uniformeProductnaamUri>http://standaarden.overheid.nl/owms/terms/gevVerlVoorwerp</uniformeProductnaamUri></enrichedData></gzd></recordData><recordPosition>8</recordPosition><extraRecordData><version:version xmlns:version="http://standaarden.overheid.nl/sru/version">full</version:version><dtf:timestamp xmlns:dtf="http://standaarden.overheid.nl/sru/dtf">2023-10-18T10:55:41.563791+02:00</dtf:timestamp><rel:rank xmlns:rel="http://standaarden.overheid.nl/sru/rel">0%</rel:rank><accept:accept xmlns:accept="info:srw/1/extensions/accept">any</accept:accept></extraRecordData></record><record><recordSchema>http://standaarden.overheid.nl/sru/</recordSchema><recordPacking>xml</recordPacking><recordData><gzd xmlns="http://standaarden.overheid.nl/sru" xmlns:overheidtr="http://standaarden.overheid.nl/tr/meta/" xmlns:overheidvd="http://standaarden.overheid.nl/vd/meta/" xmlns:overheidvb="http://standaarden.overheid.nl/vb/terms" xsi:schemaLocation="http://standaarden.overheid.nl/sru gzd.xsd"><originalData><overheidproduct:scproduct owms-version="4.0"><overheidproduct:meta><overheidproduct:owmskern><dcterms:identifier><![CDATA[https://www.voerendaal.nl/aanvragen-en-regelen/geboorte-trouwen-overlijden/naamskeuze/-naamswijziging]]></dcterms:identifier><dcterms:title><![CDATA[Naamskeuze/ naamswijziging]]></dcterms:title><dcterms:language><![CDATA[nl]]></dcterms:language><dcterms:type scheme="overheid:Informatietype">productbeschrijving</dcterms:type><dcterms:modified>2023-05-08</dcterms:modified><dcterms:spatial scheme="overheid:Gemeente" resourceIdentifier="http://standaarden.overheid.nl/owms/terms/Voerendaal_(gemeente)"><![CDATA[Voerendaal]]></dcterms:spatial><overheid:authority scheme="overheid:Gemeente" resourceIdentifier="http://standaarden.overheid.nl/owms/terms/Voerendaal_(gemeente)"><![CDATA[Voerendaal]]></overheid:authority></overheidproduct:owmskern><overheidproduct:owmsmantel><dcterms:audience scheme="overheid:Doelgroep">particulier</dcterms:audience><dcterms:abstract><![CDATA[Krijgt u een eerste kind? Afhankelijk van uw gezinssituatie, kunt u bij de gemeente aangeven welke achternaam uw kind krijgt]]></dcterms:abstract></overheidproduct:owmsmantel><overheidproduct:scmeta><overheidproduct:productID><![CDATA[53]]></overheidproduct:productID><overheidproduct:onlineAanvragen>nee</overheidproduct:onlineAanvragen></overheidproduct:scmeta></overheidproduct:meta><overheidproduct:body><overheidproduct:productHTML xsi:schemaLocation="http://www.w3.org/1999/xhtml http://www.w3.org/2002/08/xhtml/xhtml1-strict.xsd"/></overheidproduct:body></overheidproduct:scproduct></originalData><enrichedData><authorityScheme>Gemeente</authorityScheme><authorityUri>http://standaarden.overheid.nl/owms/terms/Voerendaal_(gemeente)</authorityUri><spatialType>Gemeente</spatialType><spatialUri>http://standaarden.overheid.nl/owms/terms/Voerendaal_(gemeente)</spatialUri></enrichedData></gzd></recordData><recordPosition>9</recordPosition><extraRecordData><version:version xmlns:version="http://standaarden.overheid.nl/sru/version">full</version:version><dtf:timestamp xmlns:dtf="http://standaarden.overheid.nl/sru/dtf">2023-10-18T10:55:41.563791+02:00</dtf:timestamp><rel:rank xmlns:rel="http://standaarden.overheid.nl/sru/rel">0%</rel:rank><accept:accept xmlns:accept="info:srw/1/extensions/accept">any</accept:accept></extraRecordData></record><record><recordSchema>http://standaarden.overheid.nl/sru/</recordSchema><recordPacking>xml</recordPacking><recordData><gzd xmlns="http://standaarden.overheid.nl/sru" xmlns:overheidtr="http://standaarden.overheid.nl/tr/meta/" xmlns:overheidvd="http://standaarden.overheid.nl/vd/meta/" xmlns:overheidvb="http://standaarden.overheid.nl/vb/terms" xsi:schemaLocation="http://standaarden.overheid.nl/sru gzd.xsd"><originalData><overheidproduct:scproduct owms-version="4.0"><overheidproduct:meta><overheidproduct:owmskern><dcterms:identifier><![CDATA[https://www.voerendaal.nl/aanvragen-en-regelen/subsidies/subsidie-afkoppelen-regenwater]]></dcterms:identifier><dcterms:title><![CDATA[Subsidie afkoppelen regenwater]]></dcterms:title><dcterms:language><![CDATA[nl]]></dcterms:language><dcterms:type scheme="overheid:Informatietype">productbeschrijving</dcterms:type><dcterms:modified>2023-05-08</dcterms:modified><dcterms:spatial scheme="overheid:Gemeente" resourceIdentifier="http://standaarden.overheid.nl/owms/terms/Voerendaal_(gemeente)"><![CDATA[Voerendaal]]></dcterms:spatial><overheid:authority scheme="overheid:Gemeente" resourceIdentifier="http://standaarden.overheid.nl/owms/terms/Voerendaal_(gemeente)"><![CDATA[Voerendaal]]></overheid:authority></overheidproduct:owmskern><overheidproduct:owmsmantel><dcterms:audience scheme="overheid:Doelgroep">particulier</dcterms:audience><dcterms:abstract><![CDATA[De gemeente heeft subsidie voor het afkoppelen van regenwater en het groener maken van uw tuin. Vraag de subsidie aan via de website van waterklaar.]]></dcterms:abstract></overheidproduct:owmsmantel><overheidproduct:scmeta><overheidproduct:productID><![CDATA[74]]></overheidproduct:productID><overheidproduct:onlineAanvragen>nee</overheidproduct:onlineAanvragen></overheidproduct:scmeta></overheidproduct:meta><overheidproduct:body><overheidproduct:productHTML xsi:schemaLocation="http://www.w3.org/1999/xhtml http://www.w3.org/2002/08/xhtml/xhtml1-strict.xsd"/></overheidproduct:body></overheidproduct:scproduct></originalData><enrichedData><authorityScheme>Gemeente</authorityScheme><authorityUri>http://standaarden.overheid.nl/owms/terms/Voerendaal_(gemeente)</authorityUri><spatialType>Gemeente</spatialType><spatialUri>http://standaarden.overheid.nl/owms/terms/Voerendaal_(gemeente)</spatialUri></enrichedData></gzd></recordData><recordPosition>10</recordPosition><extraRecordData><version:version xmlns:version="http://standaarden.overheid.nl/sru/version">full</version:version><dtf:timestamp xmlns:dtf="http://standaarden.overheid.nl/sru/dtf">2023-10-18T10:55:41.563791+02:00</dtf:timestamp><rel:rank xmlns:rel="http://standaarden.overheid.nl/sru/rel">0%</rel:rank><accept:accept xmlns:accept="info:srw/1/extensions/accept">any</accept:accept></extraRecordData></record><record><recordSchema>http://standaarden.overheid.nl/sru/</recordSchema><recordPacking>xml</recordPacking><recordData><gzd xmlns="http://standaarden.overheid.nl/sru" xmlns:overheidtr="http://standaarden.overheid.nl/tr/meta/" xmlns:overheidvd="http://standaarden.overheid.nl/vd/meta/" xmlns:overheidvb="http://standaarden.overheid.nl/vb/terms" xsi:schemaLocation="http://standaarden.overheid.nl/sru gzd.xsd"><originalData><overheidproduct:scproduct owms-version="4.0"><overheidproduct:meta><overheidproduct:owmskern><dcterms:identifier><![CDATA[https://www.voerendaal.nl/aanvragen-en-regelen/paspoort-id-rijbewijs-en-uittreksels/uittreksel-burgerlijke-stand]]></dcterms:identifier><dcterms:title><![CDATA[Uittreksel burgerlijke stand]]></dcterms:title><dcterms:language><![CDATA[nl]]></dcterms:language><dcterms:type scheme="overheid:Informatietype">productbeschrijving</dcterms:type><dcterms:modified>2023-05-08</dcterms:modified><dcterms:spatial scheme="overheid:Gemeente" resourceIdentifier="http://standaarden.overheid.nl/owms/terms/Voerendaal_(gemeente)"><![CDATA[Voerendaal]]></dcterms:spatial><overheid:authority scheme="overheid:Gemeente" resourceIdentifier="http://standaarden.overheid.nl/owms/terms/Voerendaal_(gemeente)"><![CDATA[Voerendaal]]></overheid:authority></overheidproduct:owmskern><overheidproduct:owmsmantel><dcterms:audience scheme="overheid:Doelgroep">particulier</dcterms:audience><dcterms:subject scheme="overheid:TaxonomieBeleidsagenda">Recht</dcterms:subject><dcterms:abstract><![CDATA[Een uittreksel burgerlijke stand vraagt u digitaal aan.]]></dcterms:abstract></overheidproduct:owmsmantel><overheidproduct:scmeta><overheidproduct:productID><![CDATA[101]]></overheidproduct:productID><overheidproduct:onlineAanvragen>nee</overheidproduct:onlineAanvragen><overheidproduct:uniformeProductnaam scheme="overheid:UniformeProductnaam" resourceIdentifier="http://standaarden.overheid.nl/owms/terms/akte_van_de_burgerlijke_stand">akte van de burgerlijke stand</overheidproduct:uniformeProductnaam></overheidproduct:scmeta></overheidproduct:meta><overheidproduct:body><overheidproduct:productHTML xsi:schemaLocation="http://www.w3.org/1999/xhtml http://www.w3.org/2002/08/xhtml/xhtml1-strict.xsd"/></overheidproduct:body></overheidproduct:scproduct></originalData><enrichedData><authorityScheme>Gemeente</authorityScheme><authorityUri>http://standaarden.overheid.nl/owms/terms/Voerendaal_(gemeente)</authorityUri><spatialType>Gemeente</spatialType><spatialUri>http://standaarden.overheid.nl/owms/terms/Voerendaal_(gemeente)</spatialUri><uniformeProductnaamUri>http://standaarden.overheid.nl/owms/terms/akte_van_de_burgerlijke_stand</uniformeProductnaamUri></enrichedData></gzd></recordData><recordPosition>11</recordPosition><extraRecordData><version:version xmlns:version="http://standaarden.overheid.nl/sru/version">full</version:version><dtf:timestamp xmlns:dtf="http://standaarden.overheid.nl/sru/dtf">2023-10-18T10:55:41.563791+02:00</dtf:timestamp><rel:rank xmlns:rel="http://standaarden.overheid.nl/sru/rel">0%</rel:rank><accept:accept xmlns:accept="info:srw/1/extensions/accept">any</accept:accept></extraRecordData></record><record><recordSchema>http://standaarden.overheid.nl/sru/</recordSchema><recordPacking>xml</recordPacking><recordData><gzd xmlns="http://standaarden.overheid.nl/sru" xmlns:overheidtr="http://standaarden.overheid.nl/tr/meta/" xmlns:overheidvd="http://standaarden.overheid.nl/vd/meta/" xmlns:overheidvb="http://standaarden.overheid.nl/vb/terms" xsi:schemaLocation="http://standaarden.overheid.nl/sru gzd.xsd"><originalData><overheidproduct:scproduct owms-version="4.0"><overheidproduct:meta><overheidproduct:owmskern><dcterms:identifier><![CDATA[https://www.voerendaal.nl/aanvragen-en-regelen/geboorte-trouwen-overlijden/attestatie-de-vita/-bewijs-van-in-leven-zijn]]></dcterms:identifier><dcterms:title><![CDATA[Attestatie de vita/ Bewijs van in leven zijn]]></dcterms:title><dcterms:language><![CDATA[nl]]></dcterms:language><dcterms:type scheme="overheid:Informatietype">productbeschrijving</dcterms:type><dcterms:modified>2023-05-08</dcterms:modified><dcterms:spatial scheme="overheid:Gemeente" resourceIdentifier="http://standaarden.overheid.nl/owms/terms/Voerendaal_(gemeente)"><![CDATA[Voerendaal]]></dcterms:spatial><overheid:authority scheme="overheid:Gemeente" resourceIdentifier="http://standaarden.overheid.nl/owms/terms/Voerendaal_(gemeente)"><![CDATA[Voerendaal]]></overheid:authority></overheidproduct:owmskern><overheidproduct:owmsmantel><dcterms:audience scheme="overheid:Doelgroep">particulier</dcterms:audience><dcterms:subject scheme="overheid:TaxonomieBeleidsagenda">Recht</dcterms:subject><dcterms:abstract><![CDATA[Een bewijs van in leven zijn of een attestatie de vita is het schriftelijke bewijs dat u volgens de BRP nog in leven bent. Vraag het persoonlijk aan.]]></dcterms:abstract></overheidproduct:owmsmantel><overheidproduct:scmeta><overheidproduct:productID><![CDATA[54]]></overheidproduct:productID><overheidproduct:onlineAanvragen>nee</overheidproduct:onlineAanvragen><overheidproduct:uniformeProductnaam scheme="overheid:UniformeProductnaam" resourceIdentifier="http://standaarden.overheid.nl/owms/terms/bewijs_van_in_leven_zijn_(attestatie_de_vita)">bewijs van in leven zijn (attestatie de vita)</overheidproduct:uniformeProductnaam></overheidproduct:scmeta></overheidproduct:meta><overheidproduct:body><overheidproduct:productHTML xsi:schemaLocation="http://www.w3.org/1999/xhtml http://www.w3.org/2002/08/xhtml/xhtml1-strict.xsd"/></overheidproduct:body></overheidproduct:scproduct></originalData><enrichedData><authorityScheme>Gemeente</authorityScheme><authorityUri>http://standaarden.overheid.nl/owms/terms/Voerendaal_(gemeente)</authorityUri><spatialType>Gemeente</spatialType><spatialUri>http://standaarden.overheid.nl/owms/terms/Voerendaal_(gemeente)</spatialUri><uniformeProductnaamUri>http://standaarden.overheid.nl/owms/terms/bewijs_van_in_leven_zijn_(attestatie_de_vita)</uniformeProductnaamUri></enrichedData></gzd></recordData><recordPosition>12</recordPosition><extraRecordData><version:version xmlns:version="http://standaarden.overheid.nl/sru/version">full</version:version><dtf:timestamp xmlns:dtf="http://standaarden.overheid.nl/sru/dtf">2023-10-18T10:55:41.563791+02:00</dtf:timestamp><rel:rank xmlns:rel="http://standaarden.overheid.nl/sru/rel">0%</rel:rank><accept:accept xmlns:accept="info:srw/1/extensions/accept">any</accept:accept></extraRecordData></record><record><recordSchema>http://standaarden.overheid.nl/sru/</recordSchema><recordPacking>xml</recordPacking><recordData><gzd xmlns="http://standaarden.overheid.nl/sru" xmlns:overheidtr="http://standaarden.overheid.nl/tr/meta/" xmlns:overheidvd="http://standaarden.overheid.nl/vd/meta/" xmlns:overheidvb="http://standaarden.overheid.nl/vb/terms" xsi:schemaLocation="http://standaarden.overheid.nl/sru gzd.xsd"><originalData><overheidproduct:scproduct owms-version="4.0"><overheidproduct:meta><overheidproduct:owmskern><dcterms:identifier><![CDATA[https://www.voerendaal.nl/aanvragen-en-regelen/paspoort-id-rijbewijs-en-uittreksels/vog-verklaring-omtrent-gedrag]]></dcterms:identifier><dcterms:title><![CDATA[VOG (verklaring omtrent gedrag)]]></dcterms:title><dcterms:language><![CDATA[nl]]></dcterms:language><dcterms:type scheme="overheid:Informatietype">productbeschrijving</dcterms:type><dcterms:modified>2023-07-18</dcterms:modified><dcterms:spatial scheme="overheid:Gemeente" resourceIdentifier="http://standaarden.overheid.nl/owms/terms/Voerendaal_(gemeente)"><![CDATA[Voerendaal]]></dcterms:spatial><overheid:authority scheme="overheid:Gemeente" resourceIdentifier="http://standaarden.overheid.nl/owms/terms/Voerendaal_(gemeente)"><![CDATA[Voerendaal]]></overheid:authority></overheidproduct:owmskern><overheidproduct:owmsmantel><dcterms:audience scheme="overheid:Doelgroep">particulier</dcterms:audience><dcterms:audience scheme="overheid:Doelgroep">ondernemer</dcterms:audience><dcterms:subject scheme="overheid:TaxonomieBeleidsagenda">Recht</dcterms:subject><dcterms:abstract><![CDATA[Een verklaring omtrent gedrag (VOG) kunt u aanvragen via uw werkgever of zelf bij de gemeente (op afspraak). De aanvraag via uw werkgever is goedkoper.]]></dcterms:abstract></overheidproduct:owmsmantel><overheidproduct:scmeta><overheidproduct:productID><![CDATA[102]]></overheidproduct:productID><overheidproduct:onlineAanvragen>nee</overheidproduct:onlineAanvragen><overheidproduct:uniformeProductnaam scheme="overheid:UniformeProductnaam" resourceIdentifier="http://standaarden.overheid.nl/owms/terms/verklaring_omtrent_gedrag_(vog)">verklaring omtrent gedrag (vog)</overheidproduct:uniformeProductnaam></overheidproduct:scmeta></overheidproduct:meta><overheidproduct:body><overheidproduct:productHTML xsi:schemaLocation="http://www.w3.org/1999/xhtml http://www.w3.org/2002/08/xhtml/xhtml1-strict.xsd"/></overheidproduct:body></overheidproduct:scproduct></originalData><enrichedData><authorityScheme>Gemeente</authorityScheme><authorityUri>http://standaarden.overheid.nl/owms/terms/Voerendaal_(gemeente)</authorityUri><spatialType>Gemeente</spatialType><spatialUri>http://standaarden.overheid.nl/owms/terms/Voerendaal_(gemeente)</spatialUri><uniformeProductnaamUri>http://standaarden.overheid.nl/owms/terms/verklaring_omtrent_gedrag_(vog)</uniformeProductnaamUri></enrichedData></gzd></recordData><recordPosition>13</recordPosition><extraRecordData><version:version xmlns:version="http://standaarden.overheid.nl/sru/version">full</version:version><dtf:timestamp xmlns:dtf="http://standaarden.overheid.nl/sru/dtf">2023-10-18T10:55:41.563791+02:00</dtf:timestamp><rel:rank xmlns:rel="http://standaarden.overheid.nl/sru/rel">0%</rel:rank><accept:accept xmlns:accept="info:srw/1/extensions/accept">any</accept:accept></extraRecordData></record><record><recordSchema>http://standaarden.overheid.nl/sru/</recordSchema><recordPacking>xml</recordPacking><recordData><gzd xmlns="http://standaarden.overheid.nl/sru" xmlns:overheidtr="http://standaarden.overheid.nl/tr/meta/" xmlns:overheidvd="http://standaarden.overheid.nl/vd/meta/" xmlns:overheidvb="http://standaarden.overheid.nl/vb/terms" xsi:schemaLocation="http://standaarden.overheid.nl/sru gzd.xsd"><originalData><overheidproduct:scproduct owms-version="4.0"><overheidproduct:meta><overheidproduct:owmskern><dcterms:identifier><![CDATA[https://www.voerendaal.nl/aanvragen-en-regelen/belastingen/hondenbelasting]]></dcterms:identifier><dcterms:title><![CDATA[Hondenbelasting]]></dcterms:title><dcterms:language><![CDATA[nl]]></dcterms:language><dcterms:type scheme="overheid:Informatietype">productbeschrijving</dcterms:type><dcterms:modified>2023-05-02</dcterms:modified><dcterms:spatial scheme="overheid:Gemeente" resourceIdentifier="http://standaarden.overheid.nl/owms/terms/Voerendaal_(gemeente)"><![CDATA[Voerendaal]]></dcterms:spatial><overheid:authority scheme="overheid:Gemeente" resourceIdentifier="http://standaarden.overheid.nl/owms/terms/Voerendaal_(gemeente)"><![CDATA[Voerendaal]]></overheid:authority></overheidproduct:owmskern><overheidproduct:owmsmantel><dcterms:audience scheme="overheid:Doelgroep">particulier</dcterms:audience><dcterms:subject scheme="overheid:TaxonomieBeleidsagenda">Financiën</dcterms:subject><dcterms:abstract><![CDATA[Heeft u één of meerdere hond(en) dan moet u hondenbel­asting betalen. Meld uw hond aan of af via de digitale belastingbalie. Bekijk de tarieven hondenbelasting.]]></dcterms:abstract></overheidproduct:owmsmantel><overheidproduct:scmeta><overheidproduct:productID><![CDATA[78]]></overheidproduct:productID><overheidproduct:onlineAanvragen>nee</overheidproduct:onlineAanvragen><overheidproduct:uniformeProductnaam scheme="overheid:UniformeProductnaam" resourceIdentifier="http://standaarden.overheid.nl/owms/terms/hondenbelasting">hondenbelasting</overheidproduct:uniformeProductnaam></overheidproduct:scmeta></overheidproduct:meta><overheidproduct:body><overheidproduct:productHTML xsi:schemaLocation="http://www.w3.org/1999/xhtml http://www.w3.org/2002/08/xhtml/xhtml1-strict.xsd"/></overheidproduct:body></overheidproduct:scproduct></originalData><enrichedData><authorityScheme>Gemeente</authorityScheme><authorityUri>http://standaarden.overheid.nl/owms/terms/Voerendaal_(gemeente)</authorityUri><spatialType>Gemeente</spatialType><spatialUri>http://standaarden.overheid.nl/owms/terms/Voerendaal_(gemeente)</spatialUri><uniformeProductnaamUri>http://standaarden.overheid.nl/owms/terms/hondenbelasting</uniformeProductnaamUri></enrichedData></gzd></recordData><recordPosition>14</recordPosition><extraRecordData><version:version xmlns:version="http://standaarden.overheid.nl/sru/version">full</version:version><dtf:timestamp xmlns:dtf="http://standaarden.overheid.nl/sru/dtf">2023-10-18T10:55:41.563791+02:00</dtf:timestamp><rel:rank xmlns:rel="http://standaarden.overheid.nl/sru/rel">0%</rel:rank><accept:accept xmlns:accept="info:srw/1/extensions/accept">any</accept:accept></extraRecordData></record><record><recordSchema>http://standaarden.overheid.nl/sru/</recordSchema><recordPacking>xml</recordPacking><recordData><gzd xmlns="http://standaarden.overheid.nl/sru" xmlns:overheidtr="http://standaarden.overheid.nl/tr/meta/" xmlns:overheidvd="http://standaarden.overheid.nl/vd/meta/" xmlns:overheidvb="http://standaarden.overheid.nl/vb/terms" xsi:schemaLocation="http://standaarden.overheid.nl/sru gzd.xsd"><originalData><overheidproduct:scproduct owms-version="4.0"><overheidproduct:meta><overheidproduct:owmskern><dcterms:identifier><![CDATA[https://www.voerendaal.nl/aanvragen-en-regelen/paspoort-id-rijbewijs-en-uittreksels/rijbewijs]]></dcterms:identifier><dcterms:title><![CDATA[Rijbewijs]]></dcterms:title><dcterms:language><![CDATA[nl]]></dcterms:language><dcterms:type scheme="overheid:Informatietype">productbeschrijving</dcterms:type><dcterms:modified>2023-05-08</dcterms:modified><dcterms:spatial scheme="overheid:Gemeente" resourceIdentifier="http://standaarden.overheid.nl/owms/terms/Voerendaal_(gemeente)"><![CDATA[Voerendaal]]></dcterms:spatial><overheid:authority scheme="overheid:Gemeente" resourceIdentifier="http://standaarden.overheid.nl/owms/terms/Voerendaal_(gemeente)"><![CDATA[Voerendaal]]></overheid:authority></overheidproduct:owmskern><overheidproduct:owmsmantel><dcterms:audience scheme="overheid:Doelgroep">particulier</dcterms:audience><dcterms:subject scheme="overheid:TaxonomieBeleidsagenda">Verkeer</dcterms:subject><dcterms:abstract><![CDATA[Maak een afspraak voor het aanvragen of verlengen van uw rijbewijs. Na 5 werkdagen ligt uw nieuwe rijbewijs klaar.]]></dcterms:abstract></overheidproduct:owmsmantel><overheidproduct:scmeta><overheidproduct:productID><![CDATA[96]]></overheidproduct:productID><overheidproduct:onlineAanvragen>nee</overheidproduct:onlineAanvragen><overheidproduct:uniformeProductnaam scheme="overheid:UniformeProductnaam" resourceIdentifier="http://standaarden.overheid.nl/owms/terms/rijbewijs">rijbewijs</overheidproduct:uniformeProductnaam><overheidproduct:uniformeProductnaam scheme="overheid:UniformeProductnaam" resourceIdentifier="http://standaarden.overheid.nl/owms/terms/rijbAanvraag">rijbewijs aanvragen</overheidproduct:uniformeProductnaam><overheidproduct:uniformeProductnaam scheme="overheid:UniformeProductnaam" resourceIdentifier="http://standaarden.overheid.nl/owms/terms/rijbGezVerkl">rijbewijs gezondheidsverklaring</overheidproduct:uniformeProductnaam><overheidproduct:uniformeProductnaam scheme="overheid:UniformeProductnaam" resourceIdentifier="http://standaarden.overheid.nl/owms/terms/rijbVerlengen">rijbewijs verlengen</overheidproduct:uniformeProductnaam></overheidproduct:scmeta></overheidproduct:meta><overheidproduct:body><overheidproduct:productHTML xsi:schemaLocation="http://www.w3.org/1999/xhtml http://www.w3.org/2002/08/xhtml/xhtml1-strict.xsd"/></overheidproduct:body></overheidproduct:scproduct></originalData><enrichedData><authorityScheme>Gemeente</authorityScheme><authorityUri>http://standaarden.overheid.nl/owms/terms/Voerendaal_(gemeente)</authorityUri><spatialType>Gemeente</spatialType><spatialUri>http://standaarden.overheid.nl/owms/terms/Voerendaal_(gemeente)</spatialUri><uniformeProductnaamUri>http://standaarden.overheid.nl/owms/terms/rijbewijs</uniformeProductnaamUri><uniformeProductnaamUri>http://standaarden.overheid.nl/owms/terms/rijbAanvraag</uniformeProductnaamUri><uniformeProductnaamUri>http://standaarden.overheid.nl/owms/terms/rijbGezVerkl</uniformeProductnaamUri><uniformeProductnaamUri>http://standaarden.overheid.nl/owms/terms/rijbVerlengen</uniformeProductnaamUri></enrichedData></gzd></recordData><recordPosition>15</recordPosition><extraRecordData><version:version xmlns:version="http://standaarden.overheid.nl/sru/version">full</version:version><dtf:timestamp xmlns:dtf="http://standaarden.overheid.nl/sru/dtf">2023-10-18T10:55:41.563791+02:00</dtf:timestamp><rel:rank xmlns:rel="http://standaarden.overheid.nl/sru/rel">0%</rel:rank><accept:accept xmlns:accept="info:srw/1/extensions/accept">any</accept:accept></extraRecordData></record><record><recordSchema>http://standaarden.overheid.nl/sru/</recordSchema><recordPacking>xml</recordPacking><recordData><gzd xmlns="http://standaarden.overheid.nl/sru" xmlns:overheidtr="http://standaarden.overheid.nl/tr/meta/" xmlns:overheidvd="http://standaarden.overheid.nl/vd/meta/" xmlns:overheidvb="http://standaarden.overheid.nl/vb/terms" xsi:schemaLocation="http://standaarden.overheid.nl/sru gzd.xsd"><originalData><overheidproduct:scproduct owms-version="4.0"><overheidproduct:meta><overheidproduct:owmskern><dcterms:identifier><![CDATA[https://www.voerendaal.nl/jeugd-wmo-werk-en-inkomen/jeugd/leerlingenvervoer]]></dcterms:identifier><dcterms:title><![CDATA[Leerlingenvervoer]]></dcterms:title><dcterms:language><![CDATA[nl]]></dcterms:language><dcterms:type scheme="overheid:Informatietype">productbeschrijving</dcterms:type><dcterms:modified>2023-05-08</dcterms:modified><dcterms:spatial scheme="overheid:Gemeente" resourceIdentifier="http://standaarden.overheid.nl/owms/terms/Voerendaal_(gemeente)"><![CDATA[Voerendaal]]></dcterms:spatial><overheid:authority scheme="overheid:Gemeente" resourceIdentifier="http://standaarden.overheid.nl/owms/terms/Voerendaal_(gemeente)"><![CDATA[Voerendaal]]></overheid:authority></overheidproduct:owmskern><overheidproduct:owmsmantel><dcterms:audience scheme="overheid:Doelgroep">particulier</dcterms:audience><dcterms:subject scheme="overheid:TaxonomieBeleidsagenda">Onderwijs en wetenschap</dcterms:subject><dcterms:abstract><![CDATA[Als uw kind niet zelfstandig naar school kan, is er voor uw kind leerlingenvervoer. De voorwaarden leest u op deze pagina. U vraagt leerlingenvervoer online aan bij de gemeente.]]></dcterms:abstract></overheidproduct:owmsmantel><overheidproduct:scmeta><overheidproduct:productID><![CDATA[45]]></overheidproduct:productID><overheidproduct:onlineAanvragen>nee</overheidproduct:onlineAanvragen><overheidproduct:uniformeProductnaam scheme="overheid:UniformeProductnaam" resourceIdentifier="http://standaarden.overheid.nl/owms/terms/leerlingenvervoer">leerlingenvervoer</overheidproduct:uniformeProductnaam></overheidproduct:scmeta></overheidproduct:meta><overheidproduct:body><overheidproduct:productHTML xsi:schemaLocation="http://www.w3.org/1999/xhtml http://www.w3.org/2002/08/xhtml/xhtml1-strict.xsd"/></overheidproduct:body></overheidproduct:scproduct></originalData><enrichedData><authorityScheme>Gemeente</authorityScheme><authorityUri>http://standaarden.overheid.nl/owms/terms/Voerendaal_(gemeente)</authorityUri><spatialType>Gemeente</spatialType><spatialUri>http://standaarden.overheid.nl/owms/terms/Voerendaal_(gemeente)</spatialUri><uniformeProductnaamUri>http://standaarden.overheid.nl/owms/terms/leerlingenvervoer</uniformeProductnaamUri></enrichedData></gzd></recordData><recordPosition>16</recordPosition><extraRecordData><version:version xmlns:version="http://standaarden.overheid.nl/sru/version">full</version:version><dtf:timestamp xmlns:dtf="http://standaarden.overheid.nl/sru/dtf">2023-10-18T10:55:41.563791+02:00</dtf:timestamp><rel:rank xmlns:rel="http://standaarden.overheid.nl/sru/rel">0%</rel:rank><accept:accept xmlns:accept="info:srw/1/extensions/accept">any</accept:accept></extraRecordData></record><record><recordSchema>http://standaarden.overheid.nl/sru/</recordSchema><recordPacking>xml</recordPacking><recordData><gzd xmlns="http://standaarden.overheid.nl/sru" xmlns:overheidtr="http://standaarden.overheid.nl/tr/meta/" xmlns:overheidvd="http://standaarden.overheid.nl/vd/meta/" xmlns:overheidvb="http://standaarden.overheid.nl/vb/terms" xsi:schemaLocation="http://standaarden.overheid.nl/sru gzd.xsd"><originalData><overheidproduct:scproduct owms-version="4.0"><overheidproduct:meta><overheidproduct:owmskern><dcterms:identifier><![CDATA[https://www.voerendaal.nl/aanvragen-en-regelen/geboorte-trouwen-overlijden/aangifte-overlijden]]></dcterms:identifier><dcterms:title><![CDATA[Aangifte overlijden]]></dcterms:title><dcterms:language><![CDATA[nl]]></dcterms:language><dcterms:type scheme="overheid:Informatietype">productbeschrijving</dcterms:type><dcterms:modified>2023-05-08</dcterms:modified><dcterms:spatial scheme="overheid:Gemeente" resourceIdentifier="http://standaarden.overheid.nl/owms/terms/Voerendaal_(gemeente)"><![CDATA[Voerendaal]]></dcterms:spatial><overheid:authority scheme="overheid:Gemeente" resourceIdentifier="http://standaarden.overheid.nl/owms/terms/Voerendaal_(gemeente)"><![CDATA[Voerendaal]]></overheid:authority></overheidproduct:owmskern><overheidproduct:owmsmantel><dcterms:audience scheme="overheid:Doelgroep">particulier</dcterms:audience><dcterms:subject scheme="overheid:TaxonomieBeleidsagenda">Recht</dcterms:subject><dcterms:abstract><![CDATA[U of de begrafenisondernemer doet aangifte van overlijden. Dit moet binnen 6 dagen na het overlijden, in de gemeente waar de persoon overleden is. ]]></dcterms:abstract></overheidproduct:owmsmantel><overheidproduct:scmeta><overheidproduct:productID><![CDATA[51]]></overheidproduct:productID><overheidproduct:onlineAanvragen>nee</overheidproduct:onlineAanvragen><overheidproduct:uniformeProductnaam scheme="overheid:UniformeProductnaam" resourceIdentifier="http://standaarden.overheid.nl/owms/terms/overlijdensaangifte">overlijdensaangifte</overheidproduct:uniformeProductnaam></overheidproduct:scmeta></overheidproduct:meta><overheidproduct:body><overheidproduct:productHTML xsi:schemaLocation="http://www.w3.org/1999/xhtml http://www.w3.org/2002/08/xhtml/xhtml1-strict.xsd"/></overheidproduct:body></overheidproduct:scproduct></originalData><enrichedData><authorityScheme>Gemeente</authorityScheme><authorityUri>http://standaarden.overheid.nl/owms/terms/Voerendaal_(gemeente)</authorityUri><spatialType>Gemeente</spatialType><spatialUri>http://standaarden.overheid.nl/owms/terms/Voerendaal_(gemeente)</spatialUri><uniformeProductnaamUri>http://standaarden.overheid.nl/owms/terms/overlijdensaangifte</uniformeProductnaamUri></enrichedData></gzd></recordData><recordPosition>17</recordPosition><extraRecordData><version:version xmlns:version="http://standaarden.overheid.nl/sru/version">full</version:version><dtf:timestamp xmlns:dtf="http://standaarden.overheid.nl/sru/dtf">2023-10-18T10:55:41.563791+02:00</dtf:timestamp><rel:rank xmlns:rel="http://standaarden.overheid.nl/sru/rel">0%</rel:rank><accept:accept xmlns:accept="info:srw/1/extensions/accept">any</accept:accept></extraRecordData></record><record><recordSchema>http://standaarden.overheid.nl/sru/</recordSchema><recordPacking>xml</recordPacking><recordData><gzd xmlns="http://standaarden.overheid.nl/sru" xmlns:overheidtr="http://standaarden.overheid.nl/tr/meta/" xmlns:overheidvd="http://standaarden.overheid.nl/vd/meta/" xmlns:overheidvb="http://standaarden.overheid.nl/vb/terms" xsi:schemaLocation="http://standaarden.overheid.nl/sru gzd.xsd"><originalData><overheidproduct:scproduct owms-version="4.0"><overheidproduct:meta><overheidproduct:owmskern><dcterms:identifier><![CDATA[https://www.voerendaal.nl/aanvragen-en-regelen/persoonsgegevens/nederlander-worden]]></dcterms:identifier><dcterms:title><![CDATA[Nederlander worden]]></dcterms:title><dcterms:language><![CDATA[nl]]></dcterms:language><dcterms:type scheme="overheid:Informatietype">productbeschrijving</dcterms:type><dcterms:modified>2023-05-08</dcterms:modified><dcterms:spatial scheme="overheid:Gemeente" resourceIdentifier="http://standaarden.overheid.nl/owms/terms/Voerendaal_(gemeente)"><![CDATA[Voerendaal]]></dcterms:spatial><overheid:authority scheme="overheid:Gemeente" resourceIdentifier="http://standaarden.overheid.nl/owms/terms/Voerendaal_(gemeente)"><![CDATA[Voerendaal]]></overheid:authority></overheidproduct:owmskern><overheidproduct:owmsmantel><dcterms:audience scheme="overheid:Doelgroep">particulier</dcterms:audience><dcterms:abstract><![CDATA[Nederlander worden kan op twee manieren: via optie of via naturalisatie. Voldoet u aan de voorwaarden, bel de gemeente dan voor een afspraak.]]></dcterms:abstract></overheidproduct:owmsmantel><overheidproduct:scmeta><overheidproduct:productID><![CDATA[83]]></overheidproduct:productID><overheidproduct:onlineAanvragen>nee</overheidproduct:onlineAanvragen></overheidproduct:scmeta></overheidproduct:meta><overheidproduct:body><overheidproduct:productHTML xsi:schemaLocation="http://www.w3.org/1999/xhtml http://www.w3.org/2002/08/xhtml/xhtml1-strict.xsd"/></overheidproduct:body></overheidproduct:scproduct></originalData><enrichedData><authorityScheme>Gemeente</authorityScheme><authorityUri>http://standaarden.overheid.nl/owms/terms/Voerendaal_(gemeente)</authorityUri><spatialType>Gemeente</spatialType><spatialUri>http://standaarden.overheid.nl/owms/terms/Voerendaal_(gemeente)</spatialUri></enrichedData></gzd></recordData><recordPosition>18</recordPosition><extraRecordData><version:version xmlns:version="http://standaarden.overheid.nl/sru/version">full</version:version><dtf:timestamp xmlns:dtf="http://standaarden.overheid.nl/sru/dtf">2023-10-18T10:55:41.563791+02:00</dtf:timestamp><rel:rank xmlns:rel="http://standaarden.overheid.nl/sru/rel">0%</rel:rank><accept:accept xmlns:accept="info:srw/1/extensions/accept">any</accept:accept></extraRecordData></record><record><recordSchema>http://standaarden.overheid.nl/sru/</recordSchema><recordPacking>xml</recordPacking><recordData><gzd xmlns="http://standaarden.overheid.nl/sru" xmlns:overheidtr="http://standaarden.overheid.nl/tr/meta/" xmlns:overheidvd="http://standaarden.overheid.nl/vd/meta/" xmlns:overheidvb="http://standaarden.overheid.nl/vb/terms" xsi:schemaLocation="http://standaarden.overheid.nl/sru gzd.xsd"><originalData><overheidproduct:scproduct owms-version="4.0"><overheidproduct:meta><overheidproduct:owmskern><dcterms:identifier><![CDATA[https://www.voerendaal.nl/jeugd-wmo-werk-en-inkomen/maatschappelijke-ondersteuning-wmo/gehandicaptenparkeerkaart]]></dcterms:identifier><dcterms:title><![CDATA[Gehandicaptenparkeerkaart]]></dcterms:title><dcterms:language><![CDATA[nl]]></dcterms:language><dcterms:type scheme="overheid:Informatietype">productbeschrijving</dcterms:type><dcterms:modified>2023-05-08</dcterms:modified><dcterms:spatial scheme="overheid:Gemeente" resourceIdentifier="http://standaarden.overheid.nl/owms/terms/Voerendaal_(gemeente)"><![CDATA[Voerendaal]]></dcterms:spatial><overheid:authority scheme="overheid:Gemeente" resourceIdentifier="http://standaarden.overheid.nl/owms/terms/Voerendaal_(gemeente)"><![CDATA[Voerendaal]]></overheid:authority></overheidproduct:owmskern><overheidproduct:owmsmantel><dcterms:audience scheme="overheid:Doelgroep">particulier</dcterms:audience><dcterms:subject scheme="overheid:TaxonomieBeleidsagenda">Verkeer</dcterms:subject><dcterms:abstract><![CDATA[Moet uw auto dichtbij staan, omdat u heel moeilijk loopt? Dan kunt u een gehandicaptenparkeerkaart aanvragen. U wordt onderzocht door een arts.]]></dcterms:abstract></overheidproduct:owmsmantel><overheidproduct:scmeta><overheidproduct:productID><![CDATA[119]]></overheidproduct:productID><overheidproduct:onlineAanvragen>nee</overheidproduct:onlineAanvragen><overheidproduct:uniformeProductnaam scheme="overheid:UniformeProductnaam" resourceIdentifier="http://standaarden.overheid.nl/owms/terms/gehandicaptenparkeerkaart">gehandicaptenparkeerkaart</overheidproduct:uniformeProductnaam><overheidproduct:uniformeProductnaam scheme="overheid:UniformeProductnaam" resourceIdentifier="http://standaarden.overheid.nl/owms/terms/gehandicaptenparkeerkaart_bestuurder">gehandicaptenparkeerkaart bestuurder</overheidproduct:uniformeProductnaam><overheidproduct:uniformeProductnaam scheme="overheid:UniformeProductnaam" resourceIdentifier="http://standaarden.overheid.nl/owms/terms/gehandicaptenparkeerkaart_instellingen">gehandicaptenparkeerkaart instellingen</overheidproduct:uniformeProductnaam><overheidproduct:uniformeProductnaam scheme="overheid:UniformeProductnaam" resourceIdentifier="http://standaarden.overheid.nl/owms/terms/gehandicaptenparkeerkaart_passagier">gehandicaptenparkeerkaart passagier</overheidproduct:uniformeProductnaam></overheidproduct:scmeta></overheidproduct:meta><overheidproduct:body><overheidproduct:productHTML xsi:schemaLocation="http://www.w3.org/1999/xhtml http://www.w3.org/2002/08/xhtml/xhtml1-strict.xsd"/></overheidproduct:body></overheidproduct:scproduct></originalData><enrichedData><authorityScheme>Gemeente</authorityScheme><authorityUri>http://standaarden.overheid.nl/owms/terms/Voerendaal_(gemeente)</authorityUri><spatialType>Gemeente</spatialType><spatialUri>http://standaarden.overheid.nl/owms/terms/Voerendaal_(gemeente)</spatialUri><uniformeProductnaamUri>http://standaarden.overheid.nl/owms/terms/gehandicaptenparkeerkaart</uniformeProductnaamUri><uniformeProductnaamUri>http://standaarden.overheid.nl/owms/terms/gehandicaptenparkeerkaart_bestuurder</uniformeProductnaamUri><uniformeProductnaamUri>http://standaarden.overheid.nl/owms/terms/gehandicaptenparkeerkaart_instellingen</uniformeProductnaamUri><uniformeProductnaamUri>http://standaarden.overheid.nl/owms/terms/gehandicaptenparkeerkaart_passagier</uniformeProductnaamUri></enrichedData></gzd></recordData><recordPosition>19</recordPosition><extraRecordData><version:version xmlns:version="http://standaarden.overheid.nl/sru/version">full</version:version><dtf:timestamp xmlns:dtf="http://standaarden.overheid.nl/sru/dtf">2023-10-18T10:55:41.563791+02:00</dtf:timestamp><rel:rank xmlns:rel="http://standaarden.overheid.nl/sru/rel">0%</rel:rank><accept:accept xmlns:accept="info:srw/1/extensions/accept">any</accept:accept></extraRecordData></record><record><recordSchema>http://standaarden.overheid.nl/sru/</recordSchema><recordPacking>xml</recordPacking><recordData><gzd xmlns="http://standaarden.overheid.nl/sru" xmlns:overheidtr="http://standaarden.overheid.nl/tr/meta/" xmlns:overheidvd="http://standaarden.overheid.nl/vd/meta/" xmlns:overheidvb="http://standaarden.overheid.nl/vb/terms" xsi:schemaLocation="http://standaarden.overheid.nl/sru gzd.xsd"><originalData><overheidproduct:scproduct owms-version="4.0"><overheidproduct:meta><overheidproduct:owmskern><dcterms:identifier><![CDATA[https://www.voerendaal.nl/jeugd-wmo-werk-en-inkomen/maatschappelijke-ondersteuning-wmo/gehandicaptenparkeerplaats]]></dcterms:identifier><dcterms:title><![CDATA[Gehandicaptenparkeerplaats]]></dcterms:title><dcterms:language><![CDATA[nl]]></dcterms:language><dcterms:type scheme="overheid:Informatietype">productbeschrijving</dcterms:type><dcterms:modified>2023-05-03</dcterms:modified><dcterms:spatial scheme="overheid:Gemeente" resourceIdentifier="http://standaarden.overheid.nl/owms/terms/Voerendaal_(gemeente)"><![CDATA[Voerendaal]]></dcterms:spatial><overheid:authority scheme="overheid:Gemeente" resourceIdentifier="http://standaarden.overheid.nl/owms/terms/Voerendaal_(gemeente)"><![CDATA[Voerendaal]]></overheid:authority></overheidproduct:owmskern><overheidproduct:owmsmantel><dcterms:audience scheme="overheid:Doelgroep">particulier</dcterms:audience><dcterms:subject scheme="overheid:TaxonomieBeleidsagenda">Verkeer</dcterms:subject><dcterms:abstract><![CDATA[Als u een gehandicaptenparkeerkaart heeft en u moet uw auto voor uw huis of werk kunnen parkeren, kunt u een gehandicaptenparkeerplaats aanvragen.]]></dcterms:abstract></overheidproduct:owmsmantel><overheidproduct:scmeta><overheidproduct:productID><![CDATA[120]]></overheidproduct:productID><overheidproduct:onlineAanvragen>nee</overheidproduct:onlineAanvragen><overheidproduct:uniformeProductnaam scheme="overheid:UniformeProductnaam" resourceIdentifier="http://standaarden.overheid.nl/owms/terms/gehandicaptenparkeerplaats">gehandicaptenparkeerplaats</overheidproduct:uniformeProductnaam></overheidproduct:scmeta></overheidproduct:meta><overheidproduct:body><overheidproduct:productHTML xsi:schemaLocation="http://www.w3.org/1999/xhtml http://www.w3.org/2002/08/xhtml/xhtml1-strict.xsd"/></overheidproduct:body></overheidproduct:scproduct></originalData><enrichedData><authorityScheme>Gemeente</authorityScheme><authorityUri>http://standaarden.overheid.nl/owms/terms/Voerendaal_(gemeente)</authorityUri><spatialType>Gemeente</spatialType><spatialUri>http://standaarden.overheid.nl/owms/terms/Voerendaal_(gemeente)</spatialUri><uniformeProductnaamUri>http://standaarden.overheid.nl/owms/terms/gehandicaptenparkeerplaats</uniformeProductnaamUri></enrichedData></gzd></recordData><recordPosition>20</recordPosition><extraRecordData><version:version xmlns:version="http://standaarden.overheid.nl/sru/version">full</version:version><dtf:timestamp xmlns:dtf="http://standaarden.overheid.nl/sru/dtf">2023-10-18T10:55:41.563791+02:00</dtf:timestamp><rel:rank xmlns:rel="http://standaarden.overheid.nl/sru/rel">0%</rel:rank><accept:accept xmlns:accept="info:srw/1/extensions/accept">any</accept:accept></extraRecordData></record><record><recordSchema>http://standaarden.overheid.nl/sru/</recordSchema><recordPacking>xml</recordPacking><recordData><gzd xmlns="http://standaarden.overheid.nl/sru" xmlns:overheidtr="http://standaarden.overheid.nl/tr/meta/" xmlns:overheidvd="http://standaarden.overheid.nl/vd/meta/" xmlns:overheidvb="http://standaarden.overheid.nl/vb/terms" xsi:schemaLocation="http://standaarden.overheid.nl/sru gzd.xsd"><originalData><overheidproduct:scproduct owms-version="4.0"><overheidproduct:meta><overheidproduct:owmskern><dcterms:identifier><![CDATA[https://www.voerendaal.nl/aanvragen-en-regelen/belastingen/bsgw]]></dcterms:identifier><dcterms:title><![CDATA[BsGW]]></dcterms:title><dcterms:language><![CDATA[nl]]></dcterms:language><dcterms:type scheme="overheid:Informatietype">productbeschrijving</dcterms:type><dcterms:modified>2023-05-08</dcterms:modified><dcterms:spatial scheme="overheid:Gemeente" resourceIdentifier="http://standaarden.overheid.nl/owms/terms/Voerendaal_(gemeente)"><![CDATA[Voerendaal]]></dcterms:spatial><overheid:authority scheme="overheid:Gemeente" resourceIdentifier="http://standaarden.overheid.nl/owms/terms/Voerendaal_(gemeente)"><![CDATA[Voerendaal]]></overheid:authority></overheidproduct:owmskern><overheidproduct:owmsmantel><dcterms:audience scheme="overheid:Doelgroep">particulier</dcterms:audience><dcterms:abstract><![CDATA[BsGW verzorgt de uitvoering van de belastingen voor Voerendaal en het Waterschap Roer en Overmaas.]]></dcterms:abstract></overheidproduct:owmsmantel><overheidproduct:scmeta><overheidproduct:productID><![CDATA[75]]></overheidproduct:productID><overheidproduct:onlineAanvragen>nee</overheidproduct:onlineAanvragen></overheidproduct:scmeta></overheidproduct:meta><overheidproduct:body><overheidproduct:productHTML xsi:schemaLocation="http://www.w3.org/1999/xhtml http://www.w3.org/2002/08/xhtml/xhtml1-strict.xsd"/></overheidproduct:body></overheidproduct:scproduct></originalData><enrichedData><authorityScheme>Gemeente</authorityScheme><authorityUri>http://standaarden.overheid.nl/owms/terms/Voerendaal_(gemeente)</authorityUri><spatialType>Gemeente</spatialType><spatialUri>http://standaarden.overheid.nl/owms/terms/Voerendaal_(gemeente)</spatialUri></enrichedData></gzd></recordData><recordPosition>21</recordPosition><extraRecordData><version:version xmlns:version="http://standaarden.overheid.nl/sru/version">full</version:version><dtf:timestamp xmlns:dtf="http://standaarden.overheid.nl/sru/dtf">2023-10-18T10:55:41.563791+02:00</dtf:timestamp><rel:rank xmlns:rel="http://standaarden.overheid.nl/sru/rel">0%</rel:rank><accept:accept xmlns:accept="info:srw/1/extensions/accept">any</accept:accept></extraRecordData></record><record><recordSchema>http://standaarden.overheid.nl/sru/</recordSchema><recordPacking>xml</recordPacking><recordData><gzd xmlns="http://standaarden.overheid.nl/sru" xmlns:overheidtr="http://standaarden.overheid.nl/tr/meta/" xmlns:overheidvd="http://standaarden.overheid.nl/vd/meta/" xmlns:overheidvb="http://standaarden.overheid.nl/vb/terms" xsi:schemaLocation="http://standaarden.overheid.nl/sru gzd.xsd"><originalData><overheidproduct:scproduct owms-version="4.0"><overheidproduct:meta><overheidproduct:owmskern><dcterms:identifier><![CDATA[https://www.voerendaal.nl/aanvragen-en-regelen/verhuizen]]></dcterms:identifier><dcterms:title><![CDATA[Verhuizen]]></dcterms:title><dcterms:language><![CDATA[nl]]></dcterms:language><dcterms:type scheme="overheid:Informatietype">productbeschrijving</dcterms:type><dcterms:modified>2023-05-08</dcterms:modified><dcterms:spatial scheme="overheid:Gemeente" resourceIdentifier="http://standaarden.overheid.nl/owms/terms/Voerendaal_(gemeente)"><![CDATA[Voerendaal]]></dcterms:spatial><overheid:authority scheme="overheid:Gemeente" resourceIdentifier="http://standaarden.overheid.nl/owms/terms/Voerendaal_(gemeente)"><![CDATA[Voerendaal]]></overheid:authority></overheidproduct:owmskern><overheidproduct:owmsmantel><dcterms:audience scheme="overheid:Doelgroep">particulier</dcterms:audience><dcterms:subject scheme="overheid:TaxonomieBeleidsagenda">Recht</dcterms:subject><dcterms:abstract><![CDATA[Geef uw verhuizing online door als u in Voerendaal gaat wonen. U hoeft uw verhuizing niet door te geven in de gemeente die u verlaat.]]></dcterms:abstract></overheidproduct:owmsmantel><overheidproduct:scmeta><overheidproduct:productID><![CDATA[40]]></overheidproduct:productID><overheidproduct:onlineAanvragen>nee</overheidproduct:onlineAanvragen><overheidproduct:uniformeProductnaam scheme="overheid:UniformeProductnaam" resourceIdentifier="http://standaarden.overheid.nl/owms/terms/verhuismelding">verhuismelding</overheidproduct:uniformeProductnaam></overheidproduct:scmeta></overheidproduct:meta><overheidproduct:body><overheidproduct:productHTML xsi:schemaLocation="http://www.w3.org/1999/xhtml http://www.w3.org/2002/08/xhtml/xhtml1-strict.xsd"/></overheidproduct:body></overheidproduct:scproduct></originalData><enrichedData><authorityScheme>Gemeente</authorityScheme><authorityUri>http://standaarden.overheid.nl/owms/terms/Voerendaal_(gemeente)</authorityUri><spatialType>Gemeente</spatialType><spatialUri>http://standaarden.overheid.nl/owms/terms/Voerendaal_(gemeente)</spatialUri><uniformeProductnaamUri>http://standaarden.overheid.nl/owms/terms/verhuismelding</uniformeProductnaamUri></enrichedData></gzd></recordData><recordPosition>22</recordPosition><extraRecordData><version:version xmlns:version="http://standaarden.overheid.nl/sru/version">full</version:version><dtf:timestamp xmlns:dtf="http://standaarden.overheid.nl/sru/dtf">2023-10-18T10:55:41.563791+02:00</dtf:timestamp><rel:rank xmlns:rel="http://standaarden.overheid.nl/sru/rel">0%</rel:rank><accept:accept xmlns:accept="info:srw/1/extensions/accept">any</accept:accept></extraRecordData></record><record><recordSchema>http://standaarden.overheid.nl/sru/</recordSchema><recordPacking>xml</recordPacking><recordData><gzd xmlns="http://standaarden.overheid.nl/sru" xmlns:overheidtr="http://standaarden.overheid.nl/tr/meta/" xmlns:overheidvd="http://standaarden.overheid.nl/vd/meta/" xmlns:overheidvb="http://standaarden.overheid.nl/vb/terms" xsi:schemaLocation="http://standaarden.overheid.nl/sru gzd.xsd"><originalData><overheidproduct:scproduct owms-version="4.0"><overheidproduct:meta><overheidproduct:owmskern><dcterms:identifier><![CDATA[https://www.voerendaal.nl/aanvragen-en-regelen/geboorte-trouwen-overlijden/aangifte-geboorte]]></dcterms:identifier><dcterms:title><![CDATA[Aangifte geboorte]]></dcterms:title><dcterms:language><![CDATA[nl]]></dcterms:language><dcterms:type scheme="overheid:Informatietype">productbeschrijving</dcterms:type><dcterms:modified>2023-05-08</dcterms:modified><dcterms:spatial scheme="overheid:Gemeente" resourceIdentifier="http://standaarden.overheid.nl/owms/terms/Voerendaal_(gemeente)"><![CDATA[Voerendaal]]></dcterms:spatial><overheid:authority scheme="overheid:Gemeente" resourceIdentifier="http://standaarden.overheid.nl/owms/terms/Voerendaal_(gemeente)"><![CDATA[Voerendaal]]></overheid:authority></overheidproduct:owmskern><overheidproduct:owmsmantel><dcterms:audience scheme="overheid:Doelgroep">particulier</dcterms:audience><dcterms:subject scheme="overheid:TaxonomieBeleidsagenda">Recht</dcterms:subject><dcterms:abstract><![CDATA[Geef de geboorte aan in de gemeente waar uw kind is geboren binnen 3 dagen na de bevalling. U kunt alleen op afspraak terecht.]]></dcterms:abstract></overheidproduct:owmsmantel><overheidproduct:scmeta><overheidproduct:productID><![CDATA[30]]></overheidproduct:productID><overheidproduct:onlineAanvragen>nee</overheidproduct:onlineAanvragen><overheidproduct:uniformeProductnaam scheme="overheid:UniformeProductnaam" resourceIdentifier="http://standaarden.overheid.nl/owms/terms/geboorteaangifte">geboorteaangifte</overheidproduct:uniformeProductnaam></overheidproduct:scmeta></overheidproduct:meta><overheidproduct:body><overheidproduct:productHTML xsi:schemaLocation="http://www.w3.org/1999/xhtml http://www.w3.org/2002/08/xhtml/xhtml1-strict.xsd"/></overheidproduct:body></overheidproduct:scproduct></originalData><enrichedData><authorityScheme>Gemeente</authorityScheme><authorityUri>http://standaarden.overheid.nl/owms/terms/Voerendaal_(gemeente)</authorityUri><spatialType>Gemeente</spatialType><spatialUri>http://standaarden.overheid.nl/owms/terms/Voerendaal_(gemeente)</spatialUri><uniformeProductnaamUri>http://standaarden.overheid.nl/owms/terms/geboorteaangifte</uniformeProductnaamUri></enrichedData></gzd></recordData><recordPosition>23</recordPosition><extraRecordData><version:version xmlns:version="http://standaarden.overheid.nl/sru/version">full</version:version><dtf:timestamp xmlns:dtf="http://standaarden.overheid.nl/sru/dtf">2023-10-18T10:55:41.563791+02:00</dtf:timestamp><rel:rank xmlns:rel="http://standaarden.overheid.nl/sru/rel">0%</rel:rank><accept:accept xmlns:accept="info:srw/1/extensions/accept">any</accept:accept></extraRecordData></record><record><recordSchema>http://standaarden.overheid.nl/sru/</recordSchema><recordPacking>xml</recordPacking><recordData><gzd xmlns="http://standaarden.overheid.nl/sru" xmlns:overheidtr="http://standaarden.overheid.nl/tr/meta/" xmlns:overheidvd="http://standaarden.overheid.nl/vd/meta/" xmlns:overheidvb="http://standaarden.overheid.nl/vb/terms" xsi:schemaLocation="http://standaarden.overheid.nl/sru gzd.xsd"><originalData><overheidproduct:scproduct owms-version="4.0"><overheidproduct:meta><overheidproduct:owmskern><dcterms:identifier><![CDATA[https://www.voerendaal.nl/aanvragen-en-regelen/geboorte-trouwen-overlijden/trouwen]]></dcterms:identifier><dcterms:title><![CDATA[Trouwen]]></dcterms:title><dcterms:language><![CDATA[nl]]></dcterms:language><dcterms:type scheme="overheid:Informatietype">productbeschrijving</dcterms:type><dcterms:modified>2023-05-08</dcterms:modified><dcterms:spatial scheme="overheid:Gemeente" resourceIdentifier="http://standaarden.overheid.nl/owms/terms/Voerendaal_(gemeente)"><![CDATA[Voerendaal]]></dcterms:spatial><overheid:authority scheme="overheid:Gemeente" resourceIdentifier="http://standaarden.overheid.nl/owms/terms/Voerendaal_(gemeente)"><![CDATA[Voerendaal]]></overheid:authority></overheidproduct:owmskern><overheidproduct:owmsmantel><dcterms:audience scheme="overheid:Doelgroep">particulier</dcterms:audience><dcterms:subject scheme="overheid:TaxonomieBeleidsagenda">Recht</dcterms:subject><dcterms:abstract><![CDATA[Wilt u trouwen of een geregistreerd partnerschap aangaan in Voerendaal. Bel voor een huwelijksdatum en voor een afspraak voor het meldingsgesprek.]]></dcterms:abstract></overheidproduct:owmsmantel><overheidproduct:scmeta><overheidproduct:productID><![CDATA[29]]></overheidproduct:productID><overheidproduct:onlineAanvragen>nee</overheidproduct:onlineAanvragen><overheidproduct:uniformeProductnaam scheme="overheid:UniformeProductnaam" resourceIdentifier="http://standaarden.overheid.nl/owms/terms/trouwlocatie">trouwlocatie</overheidproduct:uniformeProductnaam></overheidproduct:scmeta></overheidproduct:meta><overheidproduct:body><overheidproduct:productHTML xsi:schemaLocation="http://www.w3.org/1999/xhtml http://www.w3.org/2002/08/xhtml/xhtml1-strict.xsd"/></overheidproduct:body></overheidproduct:scproduct></originalData><enrichedData><authorityScheme>Gemeente</authorityScheme><authorityUri>http://standaarden.overheid.nl/owms/terms/Voerendaal_(gemeente)</authorityUri><spatialType>Gemeente</spatialType><spatialUri>http://standaarden.overheid.nl/owms/terms/Voerendaal_(gemeente)</spatialUri><uniformeProductnaamUri>http://standaarden.overheid.nl/owms/terms/trouwlocatie</uniformeProductnaamUri></enrichedData></gzd></recordData><recordPosition>24</recordPosition><extraRecordData><version:version xmlns:version="http://standaarden.overheid.nl/sru/version">full</version:version><dtf:timestamp xmlns:dtf="http://standaarden.overheid.nl/sru/dtf">2023-10-18T10:55:41.563791+02:00</dtf:timestamp><rel:rank xmlns:rel="http://standaarden.overheid.nl/sru/rel">0%</rel:rank><accept:accept xmlns:accept="info:srw/1/extensions/accept">any</accept:accept></extraRecordData></record><record><recordSchema>http://standaarden.overheid.nl/sru/</recordSchema><recordPacking>xml</recordPacking><recordData><gzd xmlns="http://standaarden.overheid.nl/sru" xmlns:overheidtr="http://standaarden.overheid.nl/tr/meta/" xmlns:overheidvd="http://standaarden.overheid.nl/vd/meta/" xmlns:overheidvb="http://standaarden.overheid.nl/vb/terms" xsi:schemaLocation="http://standaarden.overheid.nl/sru gzd.xsd"><originalData><overheidproduct:scproduct owms-version="4.0"><overheidproduct:meta><overheidproduct:owmskern><dcterms:identifier><![CDATA[https://www.voerendaal.nl/aanvragen-en-regelen/melding-klacht-en-bezwaar]]></dcterms:identifier><dcterms:title><![CDATA[Melding klacht en bezwaar]]></dcterms:title><dcterms:language><![CDATA[nl]]></dcterms:language><dcterms:type scheme="overheid:Informatietype">productbeschrijving</dcterms:type><dcterms:modified>2023-05-08</dcterms:modified><dcterms:spatial scheme="overheid:Gemeente" resourceIdentifier="http://standaarden.overheid.nl/owms/terms/Voerendaal_(gemeente)"><![CDATA[Voerendaal]]></dcterms:spatial><overheid:authority scheme="overheid:Gemeente" resourceIdentifier="http://standaarden.overheid.nl/owms/terms/Voerendaal_(gemeente)"><![CDATA[Voerendaal]]></overheid:authority></overheidproduct:owmskern><overheidproduct:owmsmantel><dcterms:audience scheme="overheid:Doelgroep">particulier</dcterms:audience><dcterms:abstract><![CDATA[Heeft u een klacht, wilt u een melding of bezwaar maken? Neem dan contact op met de gemeente. ]]></dcterms:abstract></overheidproduct:owmsmantel><overheidproduct:scmeta><overheidproduct:productID><![CDATA[139]]></overheidproduct:productID><overheidproduct:onlineAanvragen>nee</overheidproduct:onlineAanvragen></overheidproduct:scmeta></overheidproduct:meta><overheidproduct:body><overheidproduct:productHTML xsi:schemaLocation="http://www.w3.org/1999/xhtml http://www.w3.org/2002/08/xhtml/xhtml1-strict.xsd"/></overheidproduct:body></overheidproduct:scproduct></originalData><enrichedData><authorityScheme>Gemeente</authorityScheme><authorityUri>http://standaarden.overheid.nl/owms/terms/Voerendaal_(gemeente)</authorityUri><spatialType>Gemeente</spatialType><spatialUri>http://standaarden.overheid.nl/owms/terms/Voerendaal_(gemeente)</spatialUri></enrichedData></gzd></recordData><recordPosition>25</recordPosition><extraRecordData><version:version xmlns:version="http://standaarden.overheid.nl/sru/version">full</version:version><dtf:timestamp xmlns:dtf="http://standaarden.overheid.nl/sru/dtf">2023-10-18T10:55:41.563791+02:00</dtf:timestamp><rel:rank xmlns:rel="http://standaarden.overheid.nl/sru/rel">0%</rel:rank><accept:accept xmlns:accept="info:srw/1/extensions/accept">any</accept:accept></extraRecordData></record><record><recordSchema>http://standaarden.overheid.nl/sru/</recordSchema><recordPacking>xml</recordPacking><recordData><gzd xmlns="http://standaarden.overheid.nl/sru" xmlns:overheidtr="http://standaarden.overheid.nl/tr/meta/" xmlns:overheidvd="http://standaarden.overheid.nl/vd/meta/" xmlns:overheidvb="http://standaarden.overheid.nl/vb/terms" xsi:schemaLocation="http://standaarden.overheid.nl/sru gzd.xsd"><originalData><overheidproduct:scproduct owms-version="4.0"><overheidproduct:meta><overheidproduct:owmskern><dcterms:identifier><![CDATA[https://www.voerendaal.nl/aanvragen-en-regelen/paspoort-id-rijbewijs-en-uittreksels/uittreksel-persoonsgegevens-brp]]></dcterms:identifier><dcterms:title><![CDATA[Uittreksel persoonsgegevens BRP]]></dcterms:title><dcterms:language><![CDATA[nl]]></dcterms:language><dcterms:type scheme="overheid:Informatietype">productbeschrijving</dcterms:type><dcterms:modified>2023-05-08</dcterms:modified><dcterms:spatial scheme="overheid:Gemeente" resourceIdentifier="http://standaarden.overheid.nl/owms/terms/Voerendaal_(gemeente)"><![CDATA[Voerendaal]]></dcterms:spatial><overheid:authority scheme="overheid:Gemeente" resourceIdentifier="http://standaarden.overheid.nl/owms/terms/Voerendaal_(gemeente)"><![CDATA[Voerendaal]]></overheid:authority></overheidproduct:owmskern><overheidproduct:owmsmantel><dcterms:audience scheme="overheid:Doelgroep">particulier</dcterms:audience><dcterms:subject scheme="overheid:TaxonomieBeleidsagenda">Recht</dcterms:subject><dcterms:abstract><![CDATA[Een uittreksel uit de BRP (persoonlijke gegevens) vraagt u digitaal aan.]]></dcterms:abstract></overheidproduct:owmsmantel><overheidproduct:scmeta><overheidproduct:productID><![CDATA[103]]></overheidproduct:productID><overheidproduct:onlineAanvragen>nee</overheidproduct:onlineAanvragen><overheidproduct:uniformeProductnaam scheme="overheid:UniformeProductnaam" resourceIdentifier="http://standaarden.overheid.nl/owms/terms/brpUittr">brp-uittreksel</overheidproduct:uniformeProductnaam></overheidproduct:scmeta></overheidproduct:meta><overheidproduct:body><overheidproduct:productHTML xsi:schemaLocation="http://www.w3.org/1999/xhtml http://www.w3.org/2002/08/xhtml/xhtml1-strict.xsd"/></overheidproduct:body></overheidproduct:scproduct></originalData><enrichedData><authorityScheme>Gemeente</authorityScheme><authorityUri>http://standaarden.overheid.nl/owms/terms/Voerendaal_(gemeente)</authorityUri><spatialType>Gemeente</spatialType><spatialUri>http://standaarden.overheid.nl/owms/terms/Voerendaal_(gemeente)</spatialUri><uniformeProductnaamUri>http://standaarden.overheid.nl/owms/terms/brpUittr</uniformeProductnaamUri></enrichedData></gzd></recordData><recordPosition>26</recordPosition><extraRecordData><version:version xmlns:version="http://standaarden.overheid.nl/sru/version">full</version:version><dtf:timestamp xmlns:dtf="http://standaarden.overheid.nl/sru/dtf">2023-10-18T10:55:41.563791+02:00</dtf:timestamp><rel:rank xmlns:rel="http://standaarden.overheid.nl/sru/rel">0%</rel:rank><accept:accept xmlns:accept="info:srw/1/extensions/accept">any</accept:accept></extraRecordData></record><record><recordSchema>http://standaarden.overheid.nl/sru/</recordSchema><recordPacking>xml</recordPacking><recordData><gzd xmlns="http://standaarden.overheid.nl/sru" xmlns:overheidtr="http://standaarden.overheid.nl/tr/meta/" xmlns:overheidvd="http://standaarden.overheid.nl/vd/meta/" xmlns:overheidvb="http://standaarden.overheid.nl/vb/terms" xsi:schemaLocation="http://standaarden.overheid.nl/sru gzd.xsd"><originalData><overheidproduct:scproduct owms-version="4.0"><overheidproduct:meta><overheidproduct:owmskern><dcterms:identifier><![CDATA[https://www.voerendaal.nl/aanvragen-en-regelen/bouwen-en-wonen/omgevingsvergunning]]></dcterms:identifier><dcterms:title><![CDATA[Omgevingsvergunning]]></dcterms:title><dcterms:language><![CDATA[nl]]></dcterms:language><dcterms:type scheme="overheid:Informatietype">productbeschrijving</dcterms:type><dcterms:modified>2023-05-08</dcterms:modified><dcterms:spatial scheme="overheid:Gemeente" resourceIdentifier="http://standaarden.overheid.nl/owms/terms/Voerendaal_(gemeente)"><![CDATA[Voerendaal]]></dcterms:spatial><overheid:authority scheme="overheid:Gemeente" resourceIdentifier="http://standaarden.overheid.nl/owms/terms/Voerendaal_(gemeente)"><![CDATA[Voerendaal]]></overheid:authority></overheidproduct:owmskern><overheidproduct:owmsmantel><dcterms:audience scheme="overheid:Doelgroep">particulier</dcterms:audience><dcterms:audience scheme="overheid:Doelgroep">ondernemer</dcterms:audience><dcterms:subject scheme="overheid:TaxonomieBeleidsagenda">Huisvesting</dcterms:subject><dcterms:subject scheme="overheid:TaxonomieBeleidsagenda">Natuur en milieu</dcterms:subject><dcterms:abstract><![CDATA[Bent u van plan te (ver)bouwen of een bedrijf te starten? Dan moet u meestal een omgevingsvergunning aanvragen. Doe eerst de vergunningencheck.]]></dcterms:abstract></overheidproduct:owmsmantel><overheidproduct:scmeta><overheidproduct:productID><![CDATA[81]]></overheidproduct:productID><overheidproduct:onlineAanvragen>nee</overheidproduct:onlineAanvragen><overheidproduct:uniformeProductnaam scheme="overheid:UniformeProductnaam" resourceIdentifier="http://standaarden.overheid.nl/owms/terms/omgevingsvergunning">omgevingsvergunning</overheidproduct:uniformeProductnaam><overheidproduct:uniformeProductnaam scheme="overheid:UniformeProductnaam" resourceIdentifier="http://standaarden.overheid.nl/owms/terms/omgevingsvergunning_bouw">omgevingsvergunning bouw</overheidproduct:uniformeProductnaam><overheidproduct:uniformeProductnaam scheme="overheid:UniformeProductnaam" resourceIdentifier="http://standaarden.overheid.nl/owms/terms/omgevingsvergunning_kap">omgevingsvergunning kap</overheidproduct:uniformeProductnaam></overheidproduct:scmeta></overheidproduct:meta><overheidproduct:body><overheidproduct:productHTML xsi:schemaLocation="http://www.w3.org/1999/xhtml http://www.w3.org/2002/08/xhtml/xhtml1-strict.xsd"/></overheidproduct:body></overheidproduct:scproduct></originalData><enrichedData><authorityScheme>Gemeente</authorityScheme><authorityUri>http://standaarden.overheid.nl/owms/terms/Voerendaal_(gemeente)</authorityUri><spatialType>Gemeente</spatialType><spatialUri>http://standaarden.overheid.nl/owms/terms/Voerendaal_(gemeente)</spatialUri><uniformeProductnaamUri>http://standaarden.overheid.nl/owms/terms/omgevingsvergunning</uniformeProductnaamUri><uniformeProductnaamUri>http://standaarden.overheid.nl/owms/terms/omgevingsvergunning_bouw</uniformeProductnaamUri><uniformeProductnaamUri>http://standaarden.overheid.nl/owms/terms/omgevingsvergunning_kap</uniformeProductnaamUri></enrichedData></gzd></recordData><recordPosition>27</recordPosition><extraRecordData><version:version xmlns:version="http://standaarden.overheid.nl/sru/version">full</version:version><dtf:timestamp xmlns:dtf="http://standaarden.overheid.nl/sru/dtf">2023-10-18T10:55:41.563791+02:00</dtf:timestamp><rel:rank xmlns:rel="http://standaarden.overheid.nl/sru/rel">0%</rel:rank><accept:accept xmlns:accept="info:srw/1/extensions/accept">any</accept:accept></extraRecordData></record></records><extraResponseData><facetedResults xmlns="http://docs.oasis-open.org/ns/search-ws/sru-facetedResults" xsi:schemaLocation="http://docs.oasis-open.org/ns/search-ws/sru-facetedResults facetedResults.xsd"><datasource><datasourceDisplayLabel>SC</datasourceDisplayLabel><datasourceDescription>Samenwerkende catalogi</datasourceDescription><baseURL>http://zoekdienst.overheid.nl/SRUServices/SRUServices.asmx/Search</baseURL><facets><facet><facetDisplayLabel>Bevoegd gezag</facetDisplayLabel><facetDescription>Geeft het soort en de naam van de organisatie aan die verantwoordelijk is voor het publiceren van de productinformatie.</facetDescription><index>organisatietype</index><relation>=</relation><terms><term><actualTerm>gemeente</actualTerm><query>authority=="Voerendaal" AND organisatietype == "gemeente"</query><requestUrl>http://zoekdienst.overheid.nl/sru/Search?version=1.2&amp;operation=searchRetrieve&amp;x-connection=sc&amp;query=authority=="Voerendaal" AND organisatietype == "gemeente"&amp;startRecord=1&amp;maximumRecords=1000&amp;x-info-1-accept=any</requestUrl><count>27</count></term></terms></facet><facet><facetDisplayLabel>Online aanvragen</facetDisplayLabel><facetDescription>Geeft aan of het product online is aan te vragen, en zo ja of hiervoor DigiD wordt gebruikt.</facetDescription><index>overheidproduct.onlineaanvragen</index><relation>=</relation><terms><term><actualTerm>nee</actualTerm><query>authority=="Voerendaal" AND overheidproduct.onlineaanvragen == "nee"</query><requestUrl>http://zoekdienst.overheid.nl/sru/Search?version=1.2&amp;operation=searchRetrieve&amp;x-connection=sc&amp;query=authority=="Voerendaal" AND overheidproduct.onlineaanvragen == "nee"&amp;startRecord=1&amp;maximumRecords=1000&amp;x-info-1-accept=any</requestUrl><count>27</count></term></terms></facet><facet><facetDisplayLabel>Doelgroep</facetDisplayLabel><facetDescription>Aanduiding van de doelgroep waarvoor het product bedoeld is: particulier of ondernemer, of beide. In dat laatste geval wordt het element tweemaal opgenomen.</facetDescription><index>dcterms.audience</index><relation>=</relation><terms><term><actualTerm>particulier</actualTerm><query>authority=="Voerendaal" AND dcterms.audience == "particulier"</query><requestUrl>http://zoekdienst.overheid.nl/sru/Search?version=1.2&amp;operation=searchRetrieve&amp;x-connection=sc&amp;query=authority=="Voerendaal" AND dcterms.audience == "particulier"&amp;startRecord=1&amp;maximumRecords=1000&amp;x-info-1-accept=any</requestUrl><count>26</count></term><term><actualTerm>ondernemer</actualTerm><query>authority=="Voerendaal" AND dcterms.audience == "ondernemer"</query><requestUrl>http://zoekdienst.overheid.nl/sru/Search?version=1.2&amp;operation=searchRetrieve&amp;x-connection=sc&amp;query=authority=="Voerendaal" AND dcterms.audience == "ondernemer"&amp;startRecord=1&amp;maximumRecords=1000&amp;x-info-1-accept=any</requestUrl><count>4</count></term></terms></facet><facet><facetDisplayLabel>Datum laatste wijziging</facetDisplayLabel><facetDescription>Aanvankelijk de datum waarop de informatie over het product is aangemaakt, en na een wijziging de datum van laatste wijziging.</facetDescription><index>dcterms.modified</index><relation>=</relation><terms><term><actualTerm>Afgelopen jaar</actualTerm><query>authority=="Voerendaal" AND dcterms.modified = "afgelopenJaar"</query><requestUrl>http://zoekdienst.overheid.nl/sru/Search?version=1.2&amp;operation=searchRetrieve&amp;x-connection=sc&amp;query=authority=="Voerendaal" AND dcterms.modified = "afgelopenJaar"&amp;startRecord=1&amp;maximumRecords=1000&amp;x-info-1-accept=any</requestUrl><count>27</count></term></terms></facet><facet><facetDisplayLabel>Bevoegd gezag</facetDisplayLabel><facetDescription>Geeft het soort en de naam van de organisatie aan die verantwoordelijk is voor het publiceren van de productinformatie.</facetDescription><index>overheid.authority</index><relation>=</relation><terms><term><actualTerm>Voerendaal</actualTerm><query>authority=="Voerendaal" AND overheid.authority == "Voerendaal"</query><requestUrl>http://zoekdienst.overheid.nl/sru/Search?version=1.2&amp;operation=searchRetrieve&amp;x-connection=sc&amp;query=authority=="Voerendaal" AND overheid.authority == "Voerendaal"&amp;startRecord=1&amp;maximumRecords=1000&amp;x-info-1-accept=any</requestUrl><count>27</count></term></terms></facet></facets></datasource></facetedResults></extraResponseData></searchRetrieveResponse>